Workbook

Sheet Room_Dataset
A1: Room_ID | B1: Room_Number | C1: Room_Type | D1: Floor | E1: Capacity | F1: Price_Per_Night | G1: Room_Status | H1: View_Type | I1: Bed_Type | J1: AC_Type | K1: Smoking_Allowed | L1: Last_Maintenance_Date
A2: R001 | B2: 101 | C2: Family Suite | D2: 1 | E2: 6 | F2: 7700 | G2: Occupied | H2: Pool View | I2: Double | J2: Non-AC | K2: Yes
A3: R002 | B3: 102 | C3: Deluxe | D3: 1 | E3: 3 | F3: 5500 | G3: Occupied | H3: Mountain View | I3: Single | J3: AC | K3: No
A4: R003 | B4: 103 | C4: Standard | D4: 1 | E4: 2 | F4: 4800 | G4: Available | H4: City View | I4: King | J4: AC | K4: Yes
A5: R004 | B5: 104 | C5: Deluxe | D5: 1 | E5: 3 | F5: 6500 | G5: Maintenance | H5: Mountain View | I5: King | J5: AC | K5: Yes | L5: 46150
A6: R005 | B6: 105 | C6: Family Suite | D6: 1 | E6: 6 | F6: 7700 | G6: Occupied | H6: Pool View | I6: Double | J6: Non-AC | K6: Yes
A7: R006 | B7: 106 | C7: Family Suite | D7: 1 | E7: 6 | F7: 7500 | G7: Occupied | H7: Mountain View | I7: Double | J7: Non-AC | K7: No
A8: R007 | B8: 107 | C8: Standard | D8: 1 | E8: 2 | F8: 4000 | G8: Available | H8: City View | I8: King | J8: Non-AC | K8: Yes
A9: R008 | B9: 108 | C9: Standard | D9: 1 | E9: 2 | F9: 3500 | G9: Maintenance | H9: City View | I9: Double | J9: Non-AC | K9: Yes | L9: 46030
A10: R009 | B10: 109 | C10: Suite | D10: 1 | E10: 4 | F10: 6400 | G10: Available | H10: Pool View | I10: Single | J10: Non-AC | K10: No
A11: R010 | B11: 110 | C11: Deluxe | D11: 1 | E11: 3 | F11: 4200 | G11: Occupied | H11: Garden View | I11: Single | J11: Non-AC | K11: No
A12: R011 | B12: 111 | C12: Deluxe | D12: 1 | E12: 3 | F12: 6700 | G12: Available | H12: Pool View | I12: King | J12: AC | K12: Yes
A13: R012 | B13: 112 | C13: Suite | D13: 1 | E13: 4 | F13: 7000 | G13: Occupied | H13: Mountain View | I13: Single | J13: AC | K13: No
A14: R013 | B14: 113 | C14: Family Suite | D14: 1 | E14: 6 | F14: 7700 | G14: Available | H14: Pool View | I14: Double | J14: Non-AC | K14: Yes
A15: R014 | B15: 114 | C15: Deluxe | D15: 1 | E15: 3 | F15: 4500 | G15: Maintenance | H15: City View | I15: Single | J15: AC | K15: Yes | L15: 45859
A16: R015 | B16: 115 | C16: Family Suite | D16: 1 | E16: 6 | F16: 7700 | G16: Available | H16: Pool View | I16: Double | J16: Non-AC | K16: No
A17: R016 | B17: 116 | C17: Suite | D17: 1 | E17: 4 | F17: 7200 | G17: Occupied | H17: Mountain View | I17: King | J17: Non-AC | K17: No
A18: R017 | B18: 117 | C18: Standard | D18: 1 | E18: 2 | F18: 5200 | G18: Occupied | H18: Pool View | I18: King | J18: Non-AC | K18: Yes
A19: R018 | B19: 118 | C19: Deluxe | D19: 1 | E19: 3 | F19: 4700 | G19: Available | H19: Garden View | I19: Double | J19: Non-AC | K19: Yes
A20: R019 | B20: 119 | C20: Standard | D20: 1 | E20: 2 | F20: 4000 | G20: Available | H20: Mountain View | I20: Single | J20: Non-AC | K20: No
A21: R020 | B21: 120 | C21: Family Suite | D21: 1 | E21: 6 | F21: 7000 | G21: Available | H21: Garden View | I21: Double | J21: Non-AC | K21: No
A22: R021 | B22: 121 | C22: Standard | D22: 1 | E22: 2 | F22: 4200 | G22: Available | H22: Pool View | I22: Single | J22: Non-AC | K22: Yes
A23: R022 | B23: 122 | C23: Family Suite | D23: 1 | E23: 6 | F23: 7800 | G23: Available | H23: City View | I23: King | J23: AC | K23: Yes
A24: R023 | B24: 123 | C24: Suite | D24: 1 | E24: 4 | F24: 6400 | G24: Available | H24: Pool View | I24: Single | J24: Non-AC | K24: No
A25: R024 | B25: 124 | C25: Family Suite | D25: 1 | E25: 6 | F25: 7800 | G25: Available | H25: Mountain View | I25: Single | J25: AC | K25: Yes
A26: R025 | B26: 125 | C26: Deluxe | D26: 1 | E26: 3 | F26: 5000 | G26: Available | H26: Garden View | I26: Single | J26: AC | K26: No
A27: R026 | B27: 126 | C27: Suite | D27: 1 | E27: 4 | F27: 7000 | G27: Available | H27: City View | I27: King | J27: AC | K27: No
... A44: R043 | B44: 143 | C44: Family Suite | D44: 1 | E44: 6 | F44: 7000 | G44: Available | H44: Mountain View | I44: Single | J44: Non-AC | K44: No
A45: R044 | B45: 144 | C45: Deluxe | D45: 1 | E45: 3 | F45: 3700 | G45: Maintenance | H45: City View | I45: Single | J45: Non-AC | K45: Yes | L45: 45918
A46: R045 | B46: 145 | C46: Suite | D46: 1 | E46: 4 | F46: 7000 | G46: Available | H46: Mountain View | I46: Single | J46: AC | K46: No
A47: R046 | B47: 146 | C47: Standard | D47: 1 | E47: 2 | F47: 4300 | G47: Available | H47: City View | I47: Double | J47: AC | K47: Yes
A48: R047 | B48: 147 | C48: Suite | D48: 1 | E48: 4 | F48: 6500 | G48: Occupied | H48: Garden View | I48: Single | J48: AC | K48: No
A49: R048 | B49: 148 | C49: Family Suite | D49: 1 | E49: 6 | F49: 9000 | G49: Available | H49: Pool View | I49: King | J49: AC | K49: No
A50: R049 | B50: 149 | C50: Standard | D50: 1 | E50: 2 | F50: 6000 | G50: Occupied | H50: Pool View | I50: King | J50: AC | K50: Yes
A51: R050 | B51: 150 | C51: Deluxe | D51: 1 | E51: 3 | F51: 4700 | G51: Available | H51: City View | I51: King | J51: Non-AC | K51: No
A52: R051 | B52: 151 | C52: Family Suite | D52: 1 | E52: 6 | F52: 7500 | G52: Available | H52: Garden View | I52: King | J52: Non-AC | K52: Yes
A53: R052 | B53: 152 | C53: Standard | D53: 1 | E53: 2 | F53: 4700 | G53: Occupied | H53: Pool View | I53: Double | J53: Non-AC | K53: Yes
A54: R053 | B54: 153 | C54: Standard | D54: 1 | E54: 2 | F54: 4800 | G54: Occupied | H54: City View | I54: King | J54: AC | K54: Yes
A55: R054 | B55: 154 | C55: Family Suite | D55: 1 | E55: 6 | F55: 8300 | G55: Available | H55: Garden View | I55: King | J55: AC | K55: No
A56: R055 | B56: 155 | C56: Suite | D56: 1 | E56: 4 | F56: 6700 | G56: Available | H56: Mountain View | I56: Double | J56: Non-AC | K56: No
A57: R056 | B57: 156 | C57: Suite | D57: 1 | E57: 4 | F57: 7700 | G57: Available | H57: Pool View | I57: Double | J57: AC | K57: No
... A60: R059 | B60: 159 | C60: Deluxe | D60: 1 | E60: 3 | F60: 6200 | G60: Available | H60: Pool View | I60: Double | J60: AC | K60: Yes
A61: R060 | B61: 160 | C61: Family Suite | D61: 2 | E61: 6 | F61: 7000 | G61: Maintenance | H61: Garden View | I61: Double | J61: Non-AC | K61: No | L61: 45913
A62: R061 | B62: 161 | C62: Suite | D62: 2 | E62: 4 | F62: 6900 | G62: Available | H62: Pool View | I62: Double | J62: Non-AC | K62: No
A63: R062 | B63: 162 | C63: Standard | D63: 2 | E63: 2 | F63: 4200 | G63: Occupied | H63: Pool View | I63: Single | J63: Non-AC | K63: Yes
A64: R063 | B64: 163 | C64: Standard | D64: 2 | E64: 2 | F64: 4800 | G64: Available | H64: Mountain View | I64: Single | J64: AC | K64: Yes
A65: R064 | B65: 164 | C65: Suite | D65: 2 | E65: 4 | F65: 5700 | G65: Occupied | H65: City View | I65: Double | J65: Non-AC | K65: No
A66: R065 | B66: 165 | C66: Suite | D66: 2 | E66: 4 | F66: 7000 | G66: Maintenance | H66: Mountain View | I66: Single | J66: AC | K66: Yes | L66: 46193
A67: R066 | B67: 166 | C67: Standard | D67: 2 | E67: 2 | F67: 4300 | G67: Available | H67: City View | I67: Double | J67: AC | K67: Yes
A68: R067 | B68: 167 | C68: Standard | D68: 2 | E68: 2 | F68: 4800 | G68: Occupied | H68: Mountain View | I68: Single | J68: AC | K68: Yes
A69: R068 | B69: 168 | C69: Family Suite | D69: 2 | E69: 6 | F69: 6500 | G69: Available | H69: Garden View | I69: Single | J69: Non-AC | K69: Yes
A70: R069 | B70: 169 | C70: Suite | D70: 2 | E70: 4 | F70: 7000 | G70: Maintenance | H70: City View | I70: King | J70: AC | K70: No | L70: 45959
A71: R070 | B71: 170 | C71: Standard | D71: 2 | E71: 2 | F71: 4000 | G71: Available | H71: Mountain View | I71: Single | J71: Non-AC | K71: Yes
A72: R071 | B72: 171 | C72: Deluxe | D72: 2 | E72: 3 | F72: 4200 | G72: Available | H72: City View | I72: Double | J72: Non-AC | K72: No
A73: R072 | B73: 172 | C73: Suite | D73: 2 | E73: 4 | F73: 6900 | G73: Available | H73: Pool View | I73: Double | J73: Non-AC | K73: No
A74: R073 | B74: 173 | C74: Standard | D74: 2 | E74: 2 | F74: 3500 | G74: Available | H74: Garden View | I74: Single | J74: Non-AC | K74: No
A75: R074 | B75: 174 | C75: Standard | D75: 2 | E75: 2 | F75: 5000 | G75: Available | H75: Pool View | I75: Single | J75: AC | K75: No
A76: R075 | B76: 175 | C76: Suite | D76: 2 | E76: 4 | F76: 7200 | G76: Occupied | H76: Pool View | I76: Single | J76: AC | K76: No
A77: R076 | B77: 176 | C77: Suite | D77: 2 | E77: 4 | F77: 6200 | G77: Occupied | H77: City View | I77: King | J77: Non-AC | K77: Yes
A78: R077 | B78: 177 | C78: Deluxe | D78: 2 | E78: 3 | F78: 6000 | G78: Occupied | H78: Garden View | I78: King | J78: AC | K78: Yes
A79: R078 | B79: 178 | C79: Standard | D79: 2 | E79: 2 | F79: 4700 | G79: Available | H79: Pool View | I79: Double | J79: Non-AC | K79: No
A80: R079 | B80: 179 | C80: Standard | D80: 2 | E80: 2 | F80: 4700 | G80: Available | H80: Pool View | I80: Double | J80: Non-AC | K80: Yes
A81: R080 | B81: 180 | C81: Deluxe | D81: 2 | E81: 3 | F81: 5200 | G81: Available | H81: Garden View | I81: King | J81: Non-AC | K81: Yes
A82: R081 | B82: 181 | C82: Family Suite | D82: 2 | E82: 6 | F82: 8300 | G82: Available | H82: Garden View | I82: King | J82: AC | K82: No
A83: R082 | B83: 182 | C83: Family Suite | D83: 2 | E83: 6 | F83: 8000 | G83: Occupied | H83: Mountain View | I83: King | J83: Non-AC | K83: No
A84: R083 | B84: 183 | C84: Deluxe | D84: 2 | E84: 3 | F84: 5400 | G84: Maintenance | H84: Pool View | I84: Double | J84: Non-AC | K84: No | L84: 45923
A85: R084 | B85: 184 | C85: Deluxe | D85: 2 | E85: 3 | F85: 5700 | G85: Occupied | H85: Mountain View | I85: King | J85: Non-AC | K85: No

Sheet Booking_Dataset_Fact_Table 
A1: Booking_ID | B1: Cust_ID | C1: Room_ID | D1: Emp_ID | E1: Booking_Date | F1: Checkin_Date | G1: Checkout_Date | H1: Room Amount | I1: Booking_Status | J1: Stay_Days | K1: Total Amount
A2: B0001 | B2: CUST0177 | C2: R026 | D2: EMP049 | E2: 46083 | F2: 46130 | G2: 46135 | H2: 7000 | I2: Completed | J2: 5 | K2: 35000
A3: B0002 | B3: CUST0302 | C3: R071 | D3: EMP076 | E3: 46101 | F3: 46117 | H3: 4200 | I3: Confirmed | J3: 6 | K3: 25200
A4: B0003 | B4: CUST0604 | C4: R041 | D4: EMP049 | E4: 46169 | F4: 46170 | G4: 46171 | H4: 5200 | I4: Completed | J4: 1 | K4: 5200
A5: B0004 | B5: CUST0943 | C5: R005 | D5: EMP049 | E5: 46136 | F5: 46137 | H5: 7700 | I5: Checked-In | J5: 7 | K5: 53900
A6: B0005 | B6: CUST0169 | C6: R048 | D6: EMP032 | E6: 46158 | F6: 46218 | G6: 46221 | H6: 9000 | I6: Completed | J6: 3 | K6: 27000
A7: B0006 | B7: CUST1754 | C7: R018 | D7: EMP130 | E7: 46170 | F7: 46223 | H7: 4700 | I7: Confirmed | J7: 1 | K7: 4700
A8: B0007 | B8: CUST0539 | C8: R059 | D8: EMP076 | E8: 46062 | F8: 46089 | H8: 6200 | I8: Confirmed | J8: 5 | K8: 31000
A9: B0008 | B9: CUST1698 | C9: R079 | D9: EMP095 | E9: 46068 | F9: 46082 | H9: 4700 | I9: Confirmed | J9: 3 | K9: 14100
A10: B0009 | B10: CUST0563 | C10: R045 | D10: EMP087 | E10: 46077 | F10: 46158 | H10: 7000 | I10: Confirmed | J10: 4 | K10: 28000
A11: B0010 | B11: CUST0833 | C11: R029 | D11: EMP130 | E11: 46129 | F11: 46149 | H11: 7000 | I11: Confirmed | J11: 3 | K11: 21000
A12: B0011 | B12: CUST1223 | C12: R038 | D12: EMP076 | E12: 46146 | F12: 46198 | H12: 5400 | I12: Confirmed | J12: 5 | K12: 27000
A13: B0012 | B13: CUST1612 | C13: R028 | D13: EMP123 | E13: 46184 | F13: 46241 | G13: 46248 | H13: 4700 | I13: Completed | J13: 7 | K13: 32900
A14: B0013 | B14: CUST0767 | C14: R070 | D14: EMP095 | E14: 46100 | F14: 46167 | H14: 4000 | I14: Confirmed | J14: 7 | K14: 28000
A15: B0014 | B15: CUST0794 | C15: R013 | D15: EMP032 | E15: 46170 | F15: 46206 | G15: 46208 | H15: 7700 | I15: Completed | J15: 2 | K15: 15400
A16: B0015 | B16: CUST1244 | C16: R023 | D16: EMP087 | E16: 46140 | F16: 46159 | H16: 6400 | I16: Confirmed | J16: 3 | K16: 19200
A17: B0016 | B17: CUST0910 | C17: R009 | D17: EMP076 | E17: 46151 | F17: 46191 | H17: 6400 | I17: Confirmed | J17: 5 | K17: 32000
A18: B0017 | B18: CUST1046 | C18: R002 | D18: EMP144 | E18: 46045 | F18: 46055 | G18: 46060 | H18: 5500 | I18: Completed | J18: 5 | K18: 27500
A19: B0018 | B19: CUST0661 | C19: R007 | D19: EMP095 | E19: 46119 | F19: 46152 | H19: 4000 | I19: Confirmed | J19: 1 | K19: 4000
A20: B0019 | B20: CUST1222 | C20: R048 | D20: EMP087 | E20: 46197 | F20: 46226 | H20: 9000 | I20: Confirmed | J20: 3 | K20: 27000
A21: B0020 | B21: CUST1151 | C21: R064 | D21: EMP049 | E21: 46084 | F21: 46144 | G21: 46146 | H21: 5700 | I21: Completed | J21: 2 | K21: 11400
A22: B0021 | B22: CUST0768 | C22: R018 | D22: EMP095 | E22: 46198 | H22: 4700 | I22: Cancelled | J22: 0 | K22: 0
A23: B0022 | B23: CUST1351 | C23: R003 | D23: EMP076 | E23: 46074 | F23: 46145 | H23: 4800 | I23: Confirmed | J23: 4 | K23: 19200
A24: B0023 | B24: CUST1038 | C24: R015 | D24: EMP095 | E24: 46027 | F24: 46054 | H24: 7700 | I24: Confirmed | J24: 4 | K24: 30800
A25: B0024 | B25: CUST0133 | C25: R031 | D25: EMP123 | E25: 46084 | F25: 46144 | G25: 46148 | H25: 7800 | I25: Completed | J25: 4 | K25: 31200
A26: B0025 | B26: CUST0735 | C26: R084 | D26: EMP032 | E26: 46028 | F26: 46080 | G26: 46084 | H26: 5700 | I26: Completed | J26: 4 | K26: 22800
A27: B0026 | B27: CUST1774 | C27: R033 | D27: EMP049 | E27: 46147 | F27: 46148 | H27: 5000 | I27: Checked-In | J27: 1 | K27: 5000
A28: B0027 | B28: CUST1505 | C28: R020 | D28: EMP032 | E28: 46025 | F28: 46084 | G28: 46090 | H28: 7000 | I28: Completed | J28: 6 | K28: 42000
A29: B0028 | B29: CUST1280 | C29: R074 | D29: EMP076 | E29: 46097 | F29: 46124 | H29: 5000 | I29: Confirmed | J29: 2 | K29: 10000
A30: B0029 | B30: CUST1824 | C30: R042 | D30: EMP095 | E30: 46143 | F30: 46179 | H30: 5500 | I30: Confirmed | J30: 5 | K30: 27500
A31: B0030 | B31: CUST0815 | C31: R002 | D31: EMP123 | E31: 46104 | F31: 46132 | G31: 46135 | H31: 5500 | I31: Completed | J31: 3 | K31: 16500
A32: B0031 | B32: CUST1596 | C32: R078 | D32: EMP087 | E32: 46060 | F32: 46123 | H32: 4700 | I32: Confirmed | J32: 4 | K32: 18800
A33: B0032 | B33: CUST0879 | C33: R052 | D33: EMP060 | E33: 46107 | F33: 46107 | H33: 4700 | I33: Checked-In | J33: 5 | K33: 23500
A34: B0033 | B34: CUST1721 | C34: R075 | D34: EMP060 | E34: 46077 | F34: 46078 | H34: 7200 | I34: Checked-In | J34: 1 | K34: 7200
A35: B0034 | B35: CUST0330 | C35: R047 | D35: EMP123 | E35: 46108 | F35: 46109 | H35: 6500 | I35: Checked-In | J35: 6 | K35: 39000
A36: B0035 | B36: CUST1686 | C36: R067 | D36: EMP060 | E36: 46094 | F36: 46110 | G36: 46116 | H36: 4800 | I36: Completed | J36: 6 | K36: 28800
A37: B0036 | B37: CUST1780 | C37: R021 | D37: EMP087 | E37: 46178 | F37: 46215 | H37: 4200 | I37: Confirmed | J37: 5 | K37: 21000
A38: B0037 | B38: CUST1171 | C38: R026 | D38: EMP143 | E38: 46193 | F38: 46212 | G38: 46216 | H38: 7000 | I38: Completed | J38: 4 | K38: 28000
A39: B0038 | B39: CUST0613 | C39: R055 | D39: EMP076 | E39: 46086 | F39: 46176 | H39: 6700 | I39: Confirmed | J39: 4 | K39: 26800
A40: B0039 | B40: CUST0096 | C40: R049 | D40: EMP032 | E40: 46140 | F40: 46182 | G40: 46183 | H40: 6000 | I40: Completed | J40: 1 | K40: 6000
A41: B0040 | B41: CUST1733 | C41: R027 | D41: EMP035 | E41: 46040 | F41: 46041 | H41: 7000 | I41: Checked-In | J41: 2 | K41: 14000
A42: B0041 | B42: CUST0567 | C42: R018 | D42: EMP123 | E42: 46072 | F42: 46087 | G42: 46093 | H42: 4700 | I42: Completed | J42: 6 | K42: 28200
A43: B0042 | B43: CUST0007 | C43: R010 | D43: EMP143 | E43: 46155 | F43: 46185 | G43: 46188 | H43: 4200 | I43: Completed | J43: 3 | K43: 12600
A44: B0043 | B44: CUST1190 | C44: R042 | D44: EMP123 | E44: 46086 | F44: 46106 | G44: 46109 | H44: 5500 | I44: Completed | J44: 3 | K44: 16500
A45: B0044 | B45: CUST0131 | C45: R031 | D45: EMP076 | E45: 46030 | F45: 46054 | H45: 7800 | I45: Confirmed | J45: 5 | K45: 39000
A46: B0045 | B46: CUST0177 | C46: R064 | D46: EMP049 | E46: 46165 | F46: 46165 | H46: 5700 | I46: Checked-In | J46: 7 | K46: 39900
A47: B0046 | B47: CUST0407 | C47: R032 | D47: EMP095 | E47: 46073 | H47: 6500 | I47: Cancelled | J47: 0 | K47: 0
A48: B0047 | B48: CUST1403 | C48: R033 | D48: EMP060 | E48: 46197 | F48: 46215 | G48: 46222 | H48: 5000 | I48: Completed | J48: 7 | K48: 35000
A49: B0048 | B49: CUST0668 | C49: R051 | D49: EMP130 | E49: 46147 | F49: 46210 | H49: 7500 | I49: Confirmed | J49: 7 | K49: 52500
A50: B0049 | B50: CUST0622 | C50: R026 | D50: EMP130 | E50: 46072 | F50: 46157 | H50: 7000 | I50: Confirmed | J50: 3 | K50: 21000
A51: B0050 | B51: CUST1203 | C51: R056 | D51: EMP076 | E51: 46165 | F51: 46254 | H51: 7700 | I51: Confirmed | J51: 4 | K51: 30800
A52: B0051 | B52: CUST1699 | C52: R064 | D52: EMP032 | E52: 46048 | F52: 46097 | G52: 46099 | H52: 5700 | I52: Completed | J52: 2 | K52: 11400
A53: B0052 | B53: CUST0083 | C53: R058 | D53: EMP076 | E53: 46095 | H53: 7200 | I53: Cancelled | J53: 0 | K53: 0
A54: B0053 | B54: CUST0951 | C54: R024 | D54: EMP087 | E54: 46065 | F54: 46136 | H54: 7800 | I54: Confirmed | J54: 6 | K54: 46800
A55: B0054 | B55: CUST1210 | C55: R025 | D55: EMP095 | E55: 46147 | F55: 46212 | H55: 5000 | I55: Confirmed | J55: 5 | K55: 25000
A56: B0055 | B56: CUST1648 | C56: R047 | D56: EMP035 | E56: 46048 | F56: 46063 | G56: 46067 | H56: 6500 | I56: Completed | J56: 4 | K56: 26000
A57: B0056 | B57: CUST0165 | C57: R022 | D57: EMP087 | E57: 46169 | F57: 46218 | H57: 7800 | I57: Confirmed | J57: 2 | K57: 15600
A58: B0057 | B58: CUST1200 | C58: R039 | D58: EMP123 | E58: 46125 | F58: 46184 | G58: 46185 | H58: 7700 | I58: Completed | J58: 1 | K58: 7700
A59: B0058 | B59: CUST1128 | C59: R084 | D59: EMP060 | E59: 46139 | F59: 46145 | G59: 46150 | H59: 5700 | I59: Completed | J59: 5 | K59: 28500
A60: B0059 | B60: CUST0250 | C60: R043 | D60: EMP095 | E60: 46025 | F60: 46110 | H60: 7000 | I60: Confirmed | J60: 2 | K60: 14000
A61: B0060 | B61: CUST0167 | C61: R020 | D61: EMP130 | E61: 46160 | F61: 46219 | H61: 7000 | I61: Confirmed | J61: 5 | K61: 35000
A62: B0061 | B62: CUST0811 | C62: R028 | D62: EMP123 | E62: 46130 | F62: 46140 | G62: 46145 | H62: 4700 | I62: Completed | J62: 5 | K62: 23500
A63: B0062 | B63: CUST1740 | C63: R080 | D63: EMP087 | E63: 46118 | F63: 46198 | H63: 5200 | I63: Confirmed | J63: 3 | K63: 15600
A64: B0063 | B64: CUST0543 | C64: R068 | D64: EMP076 | E64: 46160 | F64: 46215 | H64: 6500 | I64: Confirmed | J64: 6 | K64: 39000
A65: B0064 | B65: CUST0538 | C65: R058 | D65: EMP095 | E65: 46177 | F65: 46258 | H65: 7200 | I65: Confirmed | J65: 6 | K65: 43200
A66: B0065 | B66: CUST0302 | C66: R061 | D66: EMP087 | E66: 46169 | F66: 46246 | H66: 6900 | I66: Confirmed | J66: 5 | K66: 34500
A67: B0066 | B67: CUST0857 | C67: R056 | D67: EMP060 | E67: 46194 | F67: 46223 | G67: 46226 | H67: 7700 | I67: Completed | J67: 3 | K67: 23100
A68: B0067 | B68: CUST1692 | C68: R050 | D68: EMP087 | E68: 46031 | F68: 46069 | H68: 4700 | I68: Confirmed | J68: 2 | K68: 9400
A69: B0068 | B69: CUST0515 | C69: R057 | D69: EMP144 | E69: 46144 | F69: 46201 | G69: 46204 | H69: 6500 | I69: Completed | J69: 3 | K69: 19500
A70: B0069 | B70: CUST0739 | C70: R047 | D70: EMP060 | E70: 46131 | F70: 46186 | G70: 46187 | H70: 6500 | I70: Completed | J70: 1 | K70: 6500
A71: B0070 | B71: CUST1687 | C71: R006 | D71: EMP143 | E71: 46106 | F71: 46126 | G71: 46133 | H71: 7500 | I71: Completed | J71: 7 | K71: 52500
A72: B0071 | B72: CUST1082 | C72: R011 | D72: EMP095 | E72: 46040 | F72: 46112 | H72: 6700 | I72: Confirmed | J72: 4 | K72: 26800
A73: B0072 | B73: CUST0256 | C73: R041 | D73: EMP130 | E73: 46050 | F73: 46062 | H73: 5200 | I73: Confirmed | J73: 2 | K73: 10400
A74: B0073 | B74: CUST0869 | C74: R073 | D74: EMP130 | E74: 46023 | F74: 46061 | H74: 3500 | I74: Confirmed | J74: 4 | K74: 14000
A75: B0074 | B75: CUST1198 | C75: R063 | D75: EMP076 | E75: 46157 | F75: 46220 | H75: 4800 | I75: Confirmed | J75: 5 | K75: 24000
A76: B0075 | B76: CUST1666 | C76: R080 | D76: EMP049 | E76: 46198 | F76: 46205 | G76: 46207 | H76: 5200 | I76: Completed | J76: 2 | K76: 10400
A77: B0076 | B77: CUST0005 | C77: R003 | D77: EMP123 | E77: 46173 | F77: 46177 | G77: 46182 | H77: 4800 | I77: Completed | J77: 5 | K77: 24000
A78: B0077 | B78: CUST1671 | C78: R019 | D78: EMP130 | E78: 46042 | F78: 46109 | H78: 4000 | I78: Confirmed | J78: 7 | K78: 28000
A79: B0078 | B79: CUST1672 | C79: R060 | D79: EMP060 | E79: 46181 | F79: 46238 | G79: 46242 | H79: 7000 | I79: Completed | J79: 4 | K79: 28000
A80: B0079 | B80: CUST0105 | C80: R039 | D80: EMP095 | E80: 46152 | F80: 46175 | H80: 7700 | I80: Confirmed | J80: 1 | K80: 7700
A81: B0080 | B81: CUST1380 | C81: R039 | D81: EMP049 | E81: 46154 | F81: 46195 | G81: 46197 | H81: 7700 | I81: Completed | J81: 2 | K81: 15400
A82: B0081 | B82: CUST1705 | C82: R057 | D82: EMP060 | E82: 46132 | F82: 46138 | G82: 46145 | H82: 6500 | I82: Completed | J82: 7 | K82: 45500
A83: B0082 | B83: CUST0780 | C83: R066 | D83: EMP087 | E83: 46024 | F83: 46052 | H83: 4300 | I83: Confirmed | J83: 3 | K83: 12900
A84: B0083 | B84: CUST1402 | C84: R013 | D84: EMP076 | E84: 46170 | F84: 46206 | H84: 7700 | I84: Confirmed | J84: 2 | K84: 15400
A85: B0084 | B85: CUST0065 | C85: R040 | D85: EMP095 | E85: 46060 | F85: 46093 | H85: 6200 | I85: Confirmed | J85: 1 | K85: 6200
A86: B0085 | B86: CUST0295 | C86: R002 | D86: EMP032 | E86: 46033 | F86: 46051 | G86: 46053 | H86: 5500 | I86: Completed | J86: 2 | K86: 11000
A87: B0086 | B87: CUST0890 | C87: R021 | D87: EMP060 | E87: 46134 | F87: 46151 | G87: 46152 | H87: 4200 | I87: Completed | J87: 1 | K87: 4200
A88: B0087 | B88: CUST0452 | C88: R032 | D88: EMP049 | E88: 46146 | F88: 46193 | G88: 46194 | H88: 6500 | I88: Completed | J88: 1 | K88: 6500
A89: B0088 | B89: CUST0628 | C89: R072 | D89: EMP130 | E89: 46055 | F89: 46122 | H89: 6900 | I89: Confirmed | J89: 1 | K89: 6900
A90: B0089 | B90: CUST1610 | C90: R034 | D90: EMP076 | E90: 46093 | F90: 46136 | H90: 7200 | I90: Confirmed | J90: 3 | K90: 21600
A91: B0090 | B91: CUST0848 | C91: R046 | D91: EMP076 | E91: 46087 | F91: 46155 | H91: 4300 | I91: Confirmed | J91: 1 | K91: 4300
A92: B0091 | B92: CUST0762 | C92: R081 | D92: EMP087 | E92: 46189 | F92: 46231 | H92: 8300 | I92: Confirmed | J92: 5 | K92: 41500
A93: B0092 | B93: CUST1597 | C93: R016 | D93: EMP087 | E93: 46057 | H93: 7200 | I93: Cancelled | J93: 0 | K93: 0
A94: B0093 | B94: CUST1499 | C94: R054 | D94: EMP076 | E94: 46039 | F94: 46106 | H94: 8300 | I94: Confirmed | J94: 5 | K94: 41500
A95: B0094 | B95: CUST0762 | C95: R079 | D95: EMP076 | E95: 46075 | F95: 46163 | H95: 4700 | I95: Confirmed | J95: 3 | K95: 14100
A96: B0095 | B96: CUST0909 | C96: R029 | D96: EMP095 | E96: 46103 | F96: 46125 | H96: 7000 | I96: Confirmed | J96: 6 | K96: 42000
A97: B0096 | B97: CUST0019 | C97: R046 | D97: EMP144 | E97: 46080 | F97: 46137 | G97: 46144 | H97: 4300 | I97: Completed | J97: 7 | K97: 30100
A98: B0097 | B98: CUST1805 | C98: R035 | D98: EMP123 | E98: 46141 | F98: 46141 | H98: 6200 | I98: Checked-In | J98: 4 | K98: 24800
A99: B0098 | B99: CUST0645 | C99: R043 | D99: EMP049 | E99: 46178 | F99: 46216 | G99: 46217 | H99: 7000 | I99: Completed | J99: 1 | K99: 7000
A100: B0099 | B100: CUST0933 | C100: R039 | D100: EMP087 | E100: 46116 | F100: 46141 | H100: 7700 | I100: Confirmed | J100: 1 | K100: 7700
...

Sheet Payment_Dataset
A1: Payment_ID | B1: Booking_ID | C1: Column3 | D1: Payment_Date | E1: Booking_Status | F1: Payment Status | G1: Amount_Paid | H1: Remainign_Amount | I1: Amount_Paid2 | J1: Remainign_Amount3 | K1: Total Amount | L1: Payment_Method | M1: Transaction_ID
A2: P00001 | B2: B0001 | C2: CUST0177 | D2: 46038 | E2: Completed | F2: Paid | G2: =IF(Payment_Dataset[[#This Row],[Booking_Status]]="Completed",VLOOKUP(Payment_Dataset[[#This Row],[Booking_ID]],Booking_Dataset_Fact_Table[],11,FALSE)/VLOOKUP(Payment_Dataset[[#This Row],[Booking_Status]],Payment_Dataset!$N$6:$P$9,3,FALSE), IF(Payment_Dataset[[#This Row],[Booking_Status]]="Checked-In",VLOOKUP(Payment_Dataset[[#This Row],[Booking_ID]],Booking_Dataset_Fact_Table[],11,FALSE)*VLOOKUP(Payment_Dataset[[#This Row],[Booking_Status]],Payment_Dataset!$N$6:$P$9,3,FALSE), IF(Payment_Dataset[[#This Row],[Booking_Status]]="Cancelled",VLOOKUP(Payment_Dataset[[#This Row],[Booking_ID]],Booking_Dataset_Fact_Table[],11,FALSE)*VLOOKUP(Payment_Dataset[[#This Row],[Booking_Status]],Payment_Dataset!$N$6:$P$9,3,FALSE), IF(Payment_Dataset[[#This Row],[Booking_Status]]="Confirmed",0)))) -> 35000 | H2: =Payment_Dataset[[#This Row],[Total Amount]]-Payment_Dataset[[#This Row],[Amount_Paid]] -> 0 | I2: 35000 | J2: 0 | K2: 35000 | L2: UPI | M2: TXN461282454
A3: P00002 | B3: B0002 | C3: CUST0302 | D3: 46132 | E3: Confirmed | F3: Pending | G3: =IF(Payment_Dataset[[#This Row],[Booking_Status]]="Completed",VLOOKUP(Payment_Dataset[[#This Row],[Booking_ID]],Booking_Dataset_Fact_Table[],11,FALSE)/VLOOKUP(Payment_Dataset[[#This Row],[Booking_Status]],Payment_Dataset!$N$6:$P$9,3,FALSE), IF(Payment_Dataset[[#This Row],[Booking_Status]]="Checked-In",VLOOKUP(Payment_Dataset[[#This Row],[Booking_ID]],Booking_Dataset_Fact_Table[],11,FALSE)*VLOOKUP(Payment_Dataset[[#This Row],[Booking_Status]],Payment_Dataset!$N$6:$P$9,3,FALSE), IF(Payment_Dataset[[#This Row],[Booking_Status]]="Cancelled",VLOOKUP(Payment_Dataset[[#This Row],[Booking_ID]],Booking_Dataset_Fact_Table[],11,FALSE)*VLOOKUP(Payment_Dataset[[#This Row],[Booking_Status]],Payment_Dataset!$N$6:$P$9,3,FALSE), IF(Payment_Dataset[[#This Row],[Booking_Status]]="Confirmed",0)))) -> 0 | H3: =Payment_Dataset[[#This Row],[Total Amount]]-Payment_Dataset[[#This Row],[Amount_Paid]] -> 25200 | I3: 0 | J3: 25200 | K3: 25200 | L3: UPI | M3: TXN575688021
A4: P00003 | B4: B0003 | C4: CUST0604 | D4: 46051 | E4: Completed | F4: Paid | G4: =IF(Payment_Dataset[[#This Row],[Booking_Status]]="Completed",VLOOKUP(Payment_Dataset[[#This Row],[Booking_ID]],Booking_Dataset_Fact_Table[],11,FALSE)/VLOOKUP(Payment_Dataset[[#This Row],[Booking_Status]],Payment_Dataset!$N$6:$P$9,3,FALSE), IF(Payment_Dataset[[#This Row],[Booking_Status]]="Checked-In",VLOOKUP(Payment_Dataset[[#This Row],[Booking_ID]],Booking_Dataset_Fact_Table[],11,FALSE)*VLOOKUP(Payment_Dataset[[#This Row],[Booking_Status]],Payment_Dataset!$N$6:$P$9,3,FALSE), IF(Payment_Dataset[[#This Row],[Booking_Status]]="Cancelled",VLOOKUP(Payment_Dataset[[#This Row],[Booking_ID]],Booking_Dataset_Fact_Table[],11,FALSE)*VLOOKUP(Payment_Dataset[[#This Row],[Booking_Status]],Payment_Dataset!$N$6:$P$9,3,FALSE), IF(Payment_Dataset[[#This Row],[Booking_Status]]="Confirmed",0)))) -> 5200 | H4: =Payment_Dataset[[#This Row],[Total Amount]]-Payment_Dataset[[#This Row],[Amount_Paid]] -> 0 | I4: 5200 | J4: 0 | K4: 5200 | L4: Cash | M4: TXN671762671
A5: P00004 | B5: B0004 | C5: CUST0943 | D5: 46023 | E5: Checked-In | F5: Partial/Advanced | G5: =IF(Payment_Dataset[[#This Row],[Booking_Status]]="Completed",VLOOKUP(Payment_Dataset[[#This Row],[Booking_ID]],Booking_Dataset_Fact_Table[],11,FALSE)/VLOOKUP(Payment_Dataset[[#This Row],[Booking_Status]],Payment_Dataset!$N$6:$P$9,3,FALSE), IF(Payment_Dataset[[#This Row],[Booking_Status]]="Checked-In",VLOOKUP(Payment_Dataset[[#This Row],[Booking_ID]],Booking_Dataset_Fact_Table[],11,FALSE)*VLOOKUP(Payment_Dataset[[#This Row],[Booking_Status]],Payment_Dataset!$N$6:$P$9,3,FALSE), IF(Payment_Dataset[[#This Row],[Booking_Status]]="Cancelled",VLOOKUP(Payment_Dataset[[#This Row],[Booking_ID]],Booking_Dataset_Fact_Table[],11,FALSE)*VLOOKUP(Payment_Dataset[[#This Row],[Booking_Status]],Payment_Dataset!$N$6:$P$9,3,FALSE), IF(Payment_Dataset[[#This Row],[Booking_Status]]="Confirmed",0)))) -> 18865 | H5: =Payment_Dataset[[#This Row],[Total Amount]]-Payment_Dataset[[#This Row],[Amount_Paid]] -> 35035 | I5: 18865 | J5: 35035 | K5: 53900 | L5: Net Banking | M5: TXN720352763
A6: P00005 | B6: B0005 | C6: CUST0169 | D6: 46039 | E6: Completed | F6: Paid | G6: =IF(Payment_Dataset[[#This Row],[Booking_Status]]="Completed",VLOOKUP(Payment_Dataset[[#This Row],[Booking_ID]],Booking_Dataset_Fact_Table[],11,FALSE)/VLOOKUP(Payment_Dataset[[#This Row],[Booking_Status]],Payment_Dataset!$N$6:$P$9,3,FALSE), IF(Payment_Dataset[[#This Row],[Booking_Status]]="Checked-In",VLOOKUP(Payment_Dataset[[#This Row],[Booking_ID]],Booking_Dataset_Fact_Table[],11,FALSE)*VLOOKUP(Payment_Dataset[[#This Row],[Booking_Status]],Payment_Dataset!$N$6:$P$9,3,FALSE), IF(Payment_Dataset[[#This Row],[Booking_Status]]="Cancelled",VLOOKUP(Payment_Dataset[[#This Row],[Booking_ID]],Booking_Dataset_Fact_Table[],11,FALSE)*VLOOKUP(Payment_Dataset[[#This Row],[Booking_Status]],Payment_Dataset!$N$6:$P$9,3,FALSE), IF(Payment_Dataset[[#This Row],[Booking_Status]]="Confirmed",0)))) -> 27000 | H6: =Payment_Dataset[[#This Row],[Total Amount]]-Payment_Dataset[[#This Row],[Amount_Paid]] -> 0 | I6: 27000 | J6: 0 | K6: 27000 | L6: Credit Card | M6: TXN801796038 | N6: Confirmed | O6: Pending | P6: 0.25 | Q6: 1 nights charge
A7: P00006 | B7: B0006 | C7: CUST1754 | D7: 46126 | E7: Confirmed | F7: Pending | G7: =IF(Payment_Dataset[[#This Row],[Booking_Status]]="Completed",VLOOKUP(Payment_Dataset[[#This Row],[Booking_ID]],Booking_Dataset_Fact_Table[],11,FALSE)/VLOOKUP(Payment_Dataset[[#This Row],[Booking_Status]],Payment_Dataset!$N$6:$P$9,3,FALSE), IF(Payment_Dataset[[#This Row],[Booking_Status]]="Checked-In",VLOOKUP(Payment_Dataset[[#This Row],[Booking_ID]],Booking_Dataset_Fact_Table[],11,FALSE)*VLOOKUP(Payment_Dataset[[#This Row],[Booking_Status]],Payment_Dataset!$N$6:$P$9,3,FALSE), IF(Payment_Dataset[[#This Row],[Booking_Status]]="Cancelled",VLOOKUP(Payment_Dataset[[#This Row],[Booking_ID]],Booking_Dataset_Fact_Table[],11,FALSE)*VLOOKUP(Payment_Dataset[[#This Row],[Booking_Status]],Payment_Dataset!$N$6:$P$9,3,FALSE), IF(Payment_Dataset[[#This Row],[Booking_Status]]="Confirmed",0)))) -> 0 | H7: =Payment_Dataset[[#This Row],[Total Amount]]-Payment_Dataset[[#This Row],[Amount_Paid]] -> 4700 | I7: 0 | J7: 4700 | K7: 4700 | L7: UPI | M7: TXN325441257 | N7: Completed | O7: Paid | P7: 1 | V7: Net Banking
A8: P00007 | B8: B0007 | C8: CUST0539 | D8: 46167 | E8: Confirmed | F8: Pending | G8: =IF(Payment_Dataset[[#This Row],[Booking_Status]]="Completed",VLOOKUP(Payment_Dataset[[#This Row],[Booking_ID]],Booking_Dataset_Fact_Table[],11,FALSE)/VLOOKUP(Payment_Dataset[[#This Row],[Booking_Status]],Payment_Dataset!$N$6:$P$9,3,FALSE), IF(Payment_Dataset[[#This Row],[Booking_Status]]="Checked-In",VLOOKUP(Payment_Dataset[[#This Row],[Booking_ID]],Booking_Dataset_Fact_Table[],11,FALSE)*VLOOKUP(Payment_Dataset[[#This Row],[Booking_Status]],Payment_Dataset!$N$6:$P$9,3,FALSE), IF(Payment_Dataset[[#This Row],[Booking_Status]]="Cancelled",VLOOKUP(Payment_Dataset[[#This Row],[Booking_ID]],Booking_Dataset_Fact_Table[],11,FALSE)*VLOOKUP(Payment_Dataset[[#This Row],[Booking_Status]],Payment_Dataset!$N$6:$P$9,3,FALSE), IF(Payment_Dataset[[#This Row],[Booking_Status]]="Confirmed",0)))) -> 0 | H8: =Payment_Dataset[[#This Row],[Total Amount]]-Payment_Dataset[[#This Row],[Amount_Paid]] -> 31000 | I8: 0 | J8: 31000 | K8: 31000 | L8: Net Banking | M8: TXN493219132 | N8: Checked-In | O8: Advanced | P8: 0.35 | V8: Cash
A9: P00008 | B9: B0008 | C9: CUST1698 | D9: 46198 | E9: Confirmed | F9: Pending | G9: =IF(Payment_Dataset[[#This Row],[Booking_Status]]="Completed",VLOOKUP(Payment_Dataset[[#This Row],[Booking_ID]],Booking_Dataset_Fact_Table[],11,FALSE)/VLOOKUP(Payment_Dataset[[#This Row],[Booking_Status]],Payment_Dataset!$N$6:$P$9,3,FALSE), IF(Payment_Dataset[[#This Row],[Booking_Status]]="Checked-In",VLOOKUP(Payment_Dataset[[#This Row],[Booking_ID]],Booking_Dataset_Fact_Table[],11,FALSE)*VLOOKUP(Payment_Dataset[[#This Row],[Booking_Status]],Payment_Dataset!$N$6:$P$9,3,FALSE), IF(Payment_Dataset[[#This Row],[Booking_Status]]="Cancelled",VLOOKUP(Payment_Dataset[[#This Row],[Booking_ID]],Booking_Dataset_Fact_Table[],11,FALSE)*VLOOKUP(Payment_Dataset[[#This Row],[Booking_Status]],Payment_Dataset!$N$6:$P$9,3,FALSE), IF(Payment_Dataset[[#This Row],[Booking_Status]]="Confirmed",0)))) -> 0 | H9: =Payment_Dataset[[#This Row],[Total Amount]]-Payment_Dataset[[#This Row],[Amount_Paid]] -> 14100 | I9: 0 | J9: 14100 | K9: 14100 | L9: Debit Card | M9: TXN578265824 | N9: Cancelled | O9: Refund | P9: 0 | V9: Debit Card
A10: P00009 | B10: B0009 | C10: CUST0563 | D10: 46098 | E10: Confirmed | F10: Pending | G10: =IF(Payment_Dataset[[#This Row],[Booking_Status]]="Completed",VLOOKUP(Payment_Dataset[[#This Row],[Booking_ID]],Booking_Dataset_Fact_Table[],11,FALSE)/VLOOKUP(Payment_Dataset[[#This Row],[Booking_Status]],Payment_Dataset!$N$6:$P$9,3,FALSE), IF(Payment_Dataset[[#This Row],[Booking_Status]]="Checked-In",VLOOKUP(Payment_Dataset[[#This Row],[Booking_ID]],Booking_Dataset_Fact_Table[],11,FALSE)*VLOOKUP(Payment_Dataset[[#This Row],[Booking_Status]],Payment_Dataset!$N$6:$P$9,3,FALSE), IF(Payment_Dataset[[#This Row],[Booking_Status]]="Cancelled",VLOOKUP(Payment_Dataset[[#This Row],[Booking_ID]],Booking_Dataset_Fact_Table[],11,FALSE)*VLOOKUP(Payment_Dataset[[#This Row],[Booking_Status]],Payment_Dataset!$N$6:$P$9,3,FALSE), IF(Payment_Dataset[[#This Row],[Booking_Status]]="Confirmed",0)))) -> 0 | H10: =Payment_Dataset[[#This Row],[Total Amount]]-Payment_Dataset[[#This Row],[Amount_Paid]] -> 28000 | I10: 0 | J10: 28000 | K10: 28000 | L10: Cash | M10: TXN261376438 | V10: UPI
A11: P00010 | B11: B0010 | C11: CUST0833 | D11: 46185 | E11: Confirmed | F11: Pending | G11: =IF(Payment_Dataset[[#This Row],[Booking_Status]]="Completed",VLOOKUP(Payment_Dataset[[#This Row],[Booking_ID]],Booking_Dataset_Fact_Table[],11,FALSE)/VLOOKUP(Payment_Dataset[[#This Row],[Booking_Status]],Payment_Dataset!$N$6:$P$9,3,FALSE), IF(Payment_Dataset[[#This Row],[Booking_Status]]="Checked-In",VLOOKUP(Payment_Dataset[[#This Row],[Booking_ID]],Booking_Dataset_Fact_Table[],11,FALSE)*VLOOKUP(Payment_Dataset[[#This Row],[Booking_Status]],Payment_Dataset!$N$6:$P$9,3,FALSE), IF(Payment_Dataset[[#This Row],[Booking_Status]]="Cancelled",VLOOKUP(Payment_Dataset[[#This Row],[Booking_ID]],Booking_Dataset_Fact_Table[],11,FALSE)*VLOOKUP(Payment_Dataset[[#This Row],[Booking_Status]],Payment_Dataset!$N$6:$P$9,3,FALSE), IF(Payment_Dataset[[#This Row],[Booking_Status]]="Confirmed",0)))) -> 0 | H11: =Payment_Dataset[[#This Row],[Total Amount]]-Payment_Dataset[[#This Row],[Amount_Paid]] -> 21000 | I11: 0 | J11: 21000 | K11: 21000 | L11: Net Banking | M11: TXN193955110 | V11: Credit Card
A12: P00011 | B12: B0011 | C12: CUST1223 | D12: 46063 | E12: Confirmed | F12: Pending | G12: =IF(Payment_Dataset[[#This Row],[Booking_Status]]="Completed",VLOOKUP(Payment_Dataset[[#This Row],[Booking_ID]],Booking_Dataset_Fact_Table[],11,FALSE)/VLOOKUP(Payment_Dataset[[#This Row],[Booking_Status]],Payment_Dataset!$N$6:$P$9,3,FALSE), IF(Payment_Dataset[[#This Row],[Booking_Status]]="Checked-In",VLOOKUP(Payment_Dataset[[#This Row],[Booking_ID]],Booking_Dataset_Fact_Table[],11,FALSE)*VLOOKUP(Payment_Dataset[[#This Row],[Booking_Status]],Payment_Dataset!$N$6:$P$9,3,FALSE), IF(Payment_Dataset[[#This Row],[Booking_Status]]="Cancelled",VLOOKUP(Payment_Dataset[[#This Row],[Booking_ID]],Booking_Dataset_Fact_Table[],11,FALSE)*VLOOKUP(Payment_Dataset[[#This Row],[Booking_Status]],Payment_Dataset!$N$6:$P$9,3,FALSE), IF(Payment_Dataset[[#This Row],[Booking_Status]]="Confirmed",0)))) -> 0 | H12: =Payment_Dataset[[#This Row],[Total Amount]]-Payment_Dataset[[#This Row],[Amount_Paid]] -> 27000 | I12: 0 | J12: 27000 | K12: 27000 | L12: Net Banking | M12: TXN128568758
A13: P00012 | B13: B0012 | C13: CUST1612 | D13: 46114 | E13: Completed | F13: Paid | G13: =IF(Payment_Dataset[[#This Row],[Booking_Status]]="Completed",VLOOKUP(Payment_Dataset[[#This Row],[Booking_ID]],Booking_Dataset_Fact_Table[],11,FALSE)/VLOOKUP(Payment_Dataset[[#This Row],[Booking_Status]],Payment_Dataset!$N$6:$P$9,3,FALSE), IF(Payment_Dataset[[#This Row],[Booking_Status]]="Checked-In",VLOOKUP(Payment_Dataset[[#This Row],[Booking_ID]],Booking_Dataset_Fact_Table[],11,FALSE)*VLOOKUP(Payment_Dataset[[#This Row],[Booking_Status]],Payment_Dataset!$N$6:$P$9,3,FALSE), IF(Payment_Dataset[[#This Row],[Booking_Status]]="Cancelled",VLOOKUP(Payment_Dataset[[#This Row],[Booking_ID]],Booking_Dataset_Fact_Table[],11,FALSE)*VLOOKUP(Payment_Dataset[[#This Row],[Booking_Status]],Payment_Dataset!$N$6:$P$9,3,FALSE), IF(Payment_Dataset[[#This Row],[Booking_Status]]="Confirmed",0)))) -> 32900 | H13: =Payment_Dataset[[#This Row],[Total Amount]]-Payment_Dataset[[#This Row],[Amount_Paid]] -> 0 | I13: 32900 | J13: 0 | K13: 32900 | L13: Cash | M13: TXN924265729 | P13: =35000*35% -> 12250
A14: P00013 | B14: B0013 | C14: CUST0767 | D14: 46045 | E14: Confirmed | F14: Pending | G14: =IF(Payment_Dataset[[#This Row],[Booking_Status]]="Completed",VLOOKUP(Payment_Dataset[[#This Row],[Booking_ID]],Booking_Dataset_Fact_Table[],11,FALSE)/VLOOKUP(Payment_Dataset[[#This Row],[Booking_Status]],Payment_Dataset!$N$6:$P$9,3,FALSE), IF(Payment_Dataset[[#This Row],[Booking_Status]]="Checked-In",VLOOKUP(Payment_Dataset[[#This Row],[Booking_ID]],Booking_Dataset_Fact_Table[],11,FALSE)*VLOOKUP(Payment_Dataset[[#This Row],[Booking_Status]],Payment_Dataset!$N$6:$P$9,3,FALSE), IF(Payment_Dataset[[#This Row],[Booking_Status]]="Cancelled",VLOOKUP(Payment_Dataset[[#This Row],[Booking_ID]],Booking_Dataset_Fact_Table[],11,FALSE)*VLOOKUP(Payment_Dataset[[#This Row],[Booking_Status]],Payment_Dataset!$N$6:$P$9,3,FALSE), IF(Payment_Dataset[[#This Row],[Booking_Status]]="Confirmed",0)))) -> 0 | H14: =Payment_Dataset[[#This Row],[Total Amount]]-Payment_Dataset[[#This Row],[Amount_Paid]] -> 28000 | I14: 0 | J14: 28000 | K14: 28000 | L14: Cash | M14: TXN734818003
A15: P00014 | B15: B0014 | C15: CUST0794 | D15: 46037 | E15: Completed | F15: Paid | G15: =IF(Payment_Dataset[[#This Row],[Booking_Status]]="Completed",VLOOKUP(Payment_Dataset[[#This Row],[Booking_ID]],Booking_Dataset_Fact_Table[],11,FALSE)/VLOOKUP(Payment_Dataset[[#This Row],[Booking_Status]],Payment_Dataset!$N$6:$P$9,3,FALSE), IF(Payment_Dataset[[#This Row],[Booking_Status]]="Checked-In",VLOOKUP(Payment_Dataset[[#This Row],[Booking_ID]],Booking_Dataset_Fact_Table[],11,FALSE)*VLOOKUP(Payment_Dataset[[#This Row],[Booking_Status]],Payment_Dataset!$N$6:$P$9,3,FALSE), IF(Payment_Dataset[[#This Row],[Booking_Status]]="Cancelled",VLOOKUP(Payment_Dataset[[#This Row],[Booking_ID]],Booking_Dataset_Fact_Table[],11,FALSE)*VLOOKUP(Payment_Dataset[[#This Row],[Booking_Status]],Payment_Dataset!$N$6:$P$9,3,FALSE), IF(Payment_Dataset[[#This Row],[Booking_Status]]="Confirmed",0)))) -> 15400 | H15: =Payment_Dataset[[#This Row],[Total Amount]]-Payment_Dataset[[#This Row],[Amount_Paid]] -> 0 | I15: 15400 | J15: 0 | K15: 15400 | L15: Net Banking | M15: TXN160437524
A16: P00015 | B16: B0015 | C16: CUST1244 | D16: 46165 | E16: Confirmed | F16: Pending | G16: =IF(Payment_Dataset[[#This Row],[Booking_Status]]="Completed",VLOOKUP(Payment_Dataset[[#This Row],[Booking_ID]],Booking_Dataset_Fact_Table[],11,FALSE)/VLOOKUP(Payment_Dataset[[#This Row],[Booking_Status]],Payment_Dataset!$N$6:$P$9,3,FALSE), IF(Payment_Dataset[[#This Row],[Booking_Status]]="Checked-In",VLOOKUP(Payment_Dataset[[#This Row],[Booking_ID]],Booking_Dataset_Fact_Table[],11,FALSE)*VLOOKUP(Payment_Dataset[[#This Row],[Booking_Status]],Payment_Dataset!$N$6:$P$9,3,FALSE), IF(Payment_Dataset[[#This Row],[Booking_Status]]="Cancelled",VLOOKUP(Payment_Dataset[[#This Row],[Booking_ID]],Booking_Dataset_Fact_Table[],11,FALSE)*VLOOKUP(Payment_Dataset[[#This Row],[Booking_Status]],Payment_Dataset!$N$6:$P$9,3,FALSE), IF(Payment_Dataset[[#This Row],[Booking_Status]]="Confirmed",0)))) -> 0 | H16: =Payment_Dataset[[#This Row],[Total Amount]]-Payment_Dataset[[#This Row],[Amount_Paid]] -> 19200 | I16: 0 | J16: 19200 | K16: 19200 | L16: UPI | M16: TXN782562250 | Q16: =IF(F20="Pending",CHOOSE(RANDBETWEEN(1,4),"UPI","Cash","Card","Net Banking"),0) -> Cash
A17: P00016 | B17: B0016 | C17: CUST0910 | D17: 46156 | E17: Confirmed | F17: Pending | G17: =IF(Payment_Dataset[[#This Row],[Booking_Status]]="Completed",VLOOKUP(Payment_Dataset[[#This Row],[Booking_ID]],Booking_Dataset_Fact_Table[],11,FALSE)/VLOOKUP(Payment_Dataset[[#This Row],[Booking_Status]],Payment_Dataset!$N$6:$P$9,3,FALSE), IF(Payment_Dataset[[#This Row],[Booking_Status]]="Checked-In",VLOOKUP(Payment_Dataset[[#This Row],[Booking_ID]],Booking_Dataset_Fact_Table[],11,FALSE)*VLOOKUP(Payment_Dataset[[#This Row],[Booking_Status]],Payment_Dataset!$N$6:$P$9,3,FALSE), IF(Payment_Dataset[[#This Row],[Booking_Status]]="Cancelled",VLOOKUP(Payment_Dataset[[#This Row],[Booking_ID]],Booking_Dataset_Fact_Table[],11,FALSE)*VLOOKUP(Payment_Dataset[[#This Row],[Booking_Status]],Payment_Dataset!$N$6:$P$9,3,FALSE), IF(Payment_Dataset[[#This Row],[Booking_Status]]="Confirmed",0)))) -> 0 | H17: =Payment_Dataset[[#This Row],[Total Amount]]-Payment_Dataset[[#This Row],[Amount_Paid]] -> 32000 | I17: 0 | J17: 32000 | K17: 32000 | L17: Net Banking | M17: TXN248102641 | Q17: =IF(F21="Pending",CHOOSE(RANDBETWEEN(1,4),"UPI","Cash","Card","Net Banking"),0) -> 0
A18: P00017 | B18: B0017 | C18: CUST1046 | D18: 46098 | E18: Completed | F18: Paid | G18: =IF(Payment_Dataset[[#This Row],[Booking_Status]]="Completed",VLOOKUP(Payment_Dataset[[#This Row],[Booking_ID]],Booking_Dataset_Fact_Table[],11,FALSE)/VLOOKUP(Payment_Dataset[[#This Row],[Booking_Status]],Payment_Dataset!$N$6:$P$9,3,FALSE), IF(Payment_Dataset[[#This Row],[Booking_Status]]="Checked-In",VLOOKUP(Payment_Dataset[[#This Row],[Booking_ID]],Booking_Dataset_Fact_Table[],11,FALSE)*VLOOKUP(Payment_Dataset[[#This Row],[Booking_Status]],Payment_Dataset!$N$6:$P$9,3,FALSE), IF(Payment_Dataset[[#This Row],[Booking_Status]]="Cancelled",VLOOKUP(Payment_Dataset[[#This Row],[Booking_ID]],Booking_Dataset_Fact_Table[],11,FALSE)*VLOOKUP(Payment_Dataset[[#This Row],[Booking_Status]],Payment_Dataset!$N$6:$P$9,3,FALSE), IF(Payment_Dataset[[#This Row],[Booking_Status]]="Confirmed",0)))) -> 27500 | H18: =Payment_Dataset[[#This Row],[Total Amount]]-Payment_Dataset[[#This Row],[Amount_Paid]] -> 0 | I18: 27500 | J18: 0 | K18: 27500 | L18: Debit Card | M18: TXN313199568 | Q18: =IF(F22="Pending",CHOOSE(RANDBETWEEN(1,4),"UPI","Cash","Card","Net Banking"),0) -> 0
A19: P00018 | B19: B0018 | C19: CUST0661 | D19: 46133 | E19: Confirmed | F19: Pending | G19: =IF(Payment_Dataset[[#This Row],[Booking_Status]]="Completed",VLOOKUP(Payment_Dataset[[#This Row],[Booking_ID]],Booking_Dataset_Fact_Table[],11,FALSE)/VLOOKUP(Payment_Dataset[[#This Row],[Booking_Status]],Payment_Dataset!$N$6:$P$9,3,FALSE), IF(Payment_Dataset[[#This Row],[Booking_Status]]="Checked-In",VLOOKUP(Payment_Dataset[[#This Row],[Booking_ID]],Booking_Dataset_Fact_Table[],11,FALSE)*VLOOKUP(Payment_Dataset[[#This Row],[Booking_Status]],Payment_Dataset!$N$6:$P$9,3,FALSE), IF(Payment_Dataset[[#This Row],[Booking_Status]]="Cancelled",VLOOKUP(Payment_Dataset[[#This Row],[Booking_ID]],Booking_Dataset_Fact_Table[],11,FALSE)*VLOOKUP(Payment_Dataset[[#This Row],[Booking_Status]],Payment_Dataset!$N$6:$P$9,3,FALSE), IF(Payment_Dataset[[#This Row],[Booking_Status]]="Confirmed",0)))) -> 0 | H19: =Payment_Dataset[[#This Row],[Total Amount]]-Payment_Dataset[[#This Row],[Amount_Paid]] -> 4000 | I19: 0 | J19: 4000 | K19: 4000 | L19: Debit Card | M19: TXN914534632 | Q19: =IF(F23="Pending",CHOOSE(RANDBETWEEN(1,4),"UPI","Cash","Card","Net Banking"),0) -> Net Banking
A20: P00019 | B20: B0019 | C20: CUST1222 | D20: 46146 | E20: Confirmed | F20: Pending | G20: =IF(Payment_Dataset[[#This Row],[Booking_Status]]="Completed",VLOOKUP(Payment_Dataset[[#This Row],[Booking_ID]],Booking_Dataset_Fact_Table[],11,FALSE)/VLOOKUP(Payment_Dataset[[#This Row],[Booking_Status]],Payment_Dataset!$N$6:$P$9,3,FALSE), IF(Payment_Dataset[[#This Row],[Booking_Status]]="Checked-In",VLOOKUP(Payment_Dataset[[#This Row],[Booking_ID]],Booking_Dataset_Fact_Table[],11,FALSE)*VLOOKUP(Payment_Dataset[[#This Row],[Booking_Status]],Payment_Dataset!$N$6:$P$9,3,FALSE), IF(Payment_Dataset[[#This Row],[Booking_Status]]="Cancelled",VLOOKUP(Payment_Dataset[[#This Row],[Booking_ID]],Booking_Dataset_Fact_Table[],11,FALSE)*VLOOKUP(Payment_Dataset[[#This Row],[Booking_Status]],Payment_Dataset!$N$6:$P$9,3,FALSE), IF(Payment_Dataset[[#This Row],[Booking_Status]]="Confirmed",0)))) -> 0 | H20: =Payment_Dataset[[#This Row],[Total Amount]]-Payment_Dataset[[#This Row],[Amount_Paid]] -> 27000 | I20: 0 | J20: 27000 | K20: 27000 | L20: Debit Card | M20: TXN260255269 | Q20: =IF(F24="Pending",CHOOSE(RANDBETWEEN(1,4),"UPI","Cash","Card","Net Banking"),0) -> Cash
A21: P00020 | B21: B0020 | C21: CUST1151 | D21: 46167 | E21: Completed | F21: Paid | G21: =IF(Payment_Dataset[[#This Row],[Booking_Status]]="Completed",VLOOKUP(Payment_Dataset[[#This Row],[Booking_ID]],Booking_Dataset_Fact_Table[],11,FALSE)/VLOOKUP(Payment_Dataset[[#This Row],[Booking_Status]],Payment_Dataset!$N$6:$P$9,3,FALSE), IF(Payment_Dataset[[#This Row],[Booking_Status]]="Checked-In",VLOOKUP(Payment_Dataset[[#This Row],[Booking_ID]],Booking_Dataset_Fact_Table[],11,FALSE)*VLOOKUP(Payment_Dataset[[#This Row],[Booking_Status]],Payment_Dataset!$N$6:$P$9,3,FALSE), IF(Payment_Dataset[[#This Row],[Booking_Status]]="Cancelled",VLOOKUP(Payment_Dataset[[#This Row],[Booking_ID]],Booking_Dataset_Fact_Table[],11,FALSE)*VLOOKUP(Payment_Dataset[[#This Row],[Booking_Status]],Payment_Dataset!$N$6:$P$9,3,FALSE), IF(Payment_Dataset[[#This Row],[Booking_Status]]="Confirmed",0)))) -> 11400 | H21: =Payment_Dataset[[#This Row],[Total Amount]]-Payment_Dataset[[#This Row],[Amount_Paid]] -> 0 | I21: 11400 | J21: 0 | K21: 11400 | L21: Cash | M21: TXN618589721 | Q21: =IF(F25="Pending",CHOOSE(RANDBETWEEN(1,4),"UPI","Cash","Card","Net Banking"),0) -> 0
A22: P00021 | B22: B0021 | C22: CUST0768 | D22: 46111 | E22: Cancelled | F22: Refund | G22: =IF(Payment_Dataset[[#This Row],[Booking_Status]]="Completed",VLOOKUP(Payment_Dataset[[#This Row],[Booking_ID]],Booking_Dataset_Fact_Table[],11,FALSE)/VLOOKUP(Payment_Dataset[[#This Row],[Booking_Status]],Payment_Dataset!$N$6:$P$9,3,FALSE), IF(Payment_Dataset[[#This Row],[Booking_Status]]="Checked-In",VLOOKUP(Payment_Dataset[[#This Row],[Booking_ID]],Booking_Dataset_Fact_Table[],11,FALSE)*VLOOKUP(Payment_Dataset[[#This Row],[Booking_Status]],Payment_Dataset!$N$6:$P$9,3,FALSE), IF(Payment_Dataset[[#This Row],[Booking_Status]]="Cancelled",VLOOKUP(Payment_Dataset[[#This Row],[Booking_ID]],Booking_Dataset_Fact_Table[],11,FALSE)*VLOOKUP(Payment_Dataset[[#This Row],[Booking_Status]],Payment_Dataset!$N$6:$P$9,3,FALSE), IF(Payment_Dataset[[#This Row],[Booking_Status]]="Confirmed",0)))) -> 0 | H22: =Payment_Dataset[[#This Row],[Total Amount]]-Payment_Dataset[[#This Row],[Amount_Paid]] -> 0 | I22: 0 | J22: 0 | K22: 0 | L22: - | M22: TXN235317167 | Q22: =IF(F26="Pending",CHOOSE(RANDBETWEEN(1,4),"UPI","Cash","Card","Net Banking"),0) -> 0
A23: P00022 | B23: B0022 | C23: CUST1351 | D23: 46145 | E23: Confirmed | F23: Pending | G23: =IF(Payment_Dataset[[#This Row],[Booking_Status]]="Completed",VLOOKUP(Payment_Dataset[[#This Row],[Booking_ID]],Booking_Dataset_Fact_Table[],11,FALSE)/VLOOKUP(Payment_Dataset[[#This Row],[Booking_Status]],Payment_Dataset!$N$6:$P$9,3,FALSE), IF(Payment_Dataset[[#This Row],[Booking_Status]]="Checked-In",VLOOKUP(Payment_Dataset[[#This Row],[Booking_ID]],Booking_Dataset_Fact_Table[],11,FALSE)*VLOOKUP(Payment_Dataset[[#This Row],[Booking_Status]],Payment_Dataset!$N$6:$P$9,3,FALSE), IF(Payment_Dataset[[#This Row],[Booking_Status]]="Cancelled",VLOOKUP(Payment_Dataset[[#This Row],[Booking_ID]],Booking_Dataset_Fact_Table[],11,FALSE)*VLOOKUP(Payment_Dataset[[#This Row],[Booking_Status]],Payment_Dataset!$N$6:$P$9,3,FALSE), IF(Payment_Dataset[[#This Row],[Booking_Status]]="Confirmed",0)))) -> 0 | H23: =Payment_Dataset[[#This Row],[Total Amount]]-Payment_Dataset[[#This Row],[Amount_Paid]] -> 19200 | I23: 0 | J23: 19200 | K23: 19200 | L23: Net Banking | M23: TXN497251754 | Q23: =IF(F27="Pending",CHOOSE(RANDBETWEEN(1,4),"UPI","Cash","Card","Net Banking"),0) -> 0
A24: P00023 | B24: B0023 | C24: CUST1038 | D24: 46090 | E24: Confirmed | F24: Pending | G24: =IF(Payment_Dataset[[#This Row],[Booking_Status]]="Completed",VLOOKUP(Payment_Dataset[[#This Row],[Booking_ID]],Booking_Dataset_Fact_Table[],11,FALSE)/VLOOKUP(Payment_Dataset[[#This Row],[Booking_Status]],Payment_Dataset!$N$6:$P$9,3,FALSE), IF(Payment_Dataset[[#This Row],[Booking_Status]]="Checked-In",VLOOKUP(Payment_Dataset[[#This Row],[Booking_ID]],Booking_Dataset_Fact_Table[],11,FALSE)*VLOOKUP(Payment_Dataset[[#This Row],[Booking_Status]],Payment_Dataset!$N$6:$P$9,3,FALSE), IF(Payment_Dataset[[#This Row],[Booking_Status]]="Cancelled",VLOOKUP(Payment_Dataset[[#This Row],[Booking_ID]],Booking_Dataset_Fact_Table[],11,FALSE)*VLOOKUP(Payment_Dataset[[#This Row],[Booking_Status]],Payment_Dataset!$N$6:$P$9,3,FALSE), IF(Payment_Dataset[[#This Row],[Booking_Status]]="Confirmed",0)))) -> 0 | H24: =Payment_Dataset[[#This Row],[Total Amount]]-Payment_Dataset[[#This Row],[Amount_Paid]] -> 30800 | I24: 0 | J24: 30800 | K24: 30800 | L24: Net Banking | M24: TXN856863242 | Q24: =IF(F28="Pending",CHOOSE(RANDBETWEEN(1,4),"UPI","Cash","Card","Net Banking"),0) -> 0
A25: P00024 | B25: B0024 | C25: CUST0133 | D25: 46062 | E25: Completed | F25: Paid | G25: =IF(Payment_Dataset[[#This Row],[Booking_Status]]="Completed",VLOOKUP(Payment_Dataset[[#This Row],[Booking_ID]],Booking_Dataset_Fact_Table[],11,FALSE)/VLOOKUP(Payment_Dataset[[#This Row],[Booking_Status]],Payment_Dataset!$N$6:$P$9,3,FALSE), IF(Payment_Dataset[[#This Row],[Booking_Status]]="Checked-In",VLOOKUP(Payment_Dataset[[#This Row],[Booking_ID]],Booking_Dataset_Fact_Table[],11,FALSE)*VLOOKUP(Payment_Dataset[[#This Row],[Booking_Status]],Payment_Dataset!$N$6:$P$9,3,FALSE), IF(Payment_Dataset[[#This Row],[Booking_Status]]="Cancelled",VLOOKUP(Payment_Dataset[[#This Row],[Booking_ID]],Booking_Dataset_Fact_Table[],11,FALSE)*VLOOKUP(Payment_Dataset[[#This Row],[Booking_Status]],Payment_Dataset!$N$6:$P$9,3,FALSE), IF(Payment_Dataset[[#This Row],[Booking_Status]]="Confirmed",0)))) -> 31200 | H25: =Payment_Dataset[[#This Row],[Total Amount]]-Payment_Dataset[[#This Row],[Amount_Paid]] -> 0 | I25: 31200 | J25: 0 | K25: 31200 | L25: Debit Card | M25: TXN823433747 | Q25: =IF(F29="Pending",CHOOSE(RANDBETWEEN(1,4),"UPI","Cash","Card","Net Banking"),0) -> Net Banking
A26: P00025 | B26: B0025 | C26: CUST0735 | D26: 46101 | E26: Completed | F26: Paid | G26: =IF(Payment_Dataset[[#This Row],[Booking_Status]]="Completed",VLOOKUP(Payment_Dataset[[#This Row],[Booking_ID]],Booking_Dataset_Fact_Table[],11,FALSE)/VLOOKUP(Payment_Dataset[[#This Row],[Booking_Status]],Payment_Dataset!$N$6:$P$9,3,FALSE), IF(Payment_Dataset[[#This Row],[Booking_Status]]="Checked-In",VLOOKUP(Payment_Dataset[[#This Row],[Booking_ID]],Booking_Dataset_Fact_Table[],11,FALSE)*VLOOKUP(Payment_Dataset[[#This Row],[Booking_Status]],Payment_Dataset!$N$6:$P$9,3,FALSE), IF(Payment_Dataset[[#This Row],[Booking_Status]]="Cancelled",VLOOKUP(Payment_Dataset[[#This Row],[Booking_ID]],Booking_Dataset_Fact_Table[],11,FALSE)*VLOOKUP(Payment_Dataset[[#This Row],[Booking_Status]],Payment_Dataset!$N$6:$P$9,3,FALSE), IF(Payment_Dataset[[#This Row],[Booking_Status]]="Confirmed",0)))) -> 22800 | H26: =Payment_Dataset[[#This Row],[Total Amount]]-Payment_Dataset[[#This Row],[Amount_Paid]] -> 0 | I26: 22800 | J26: 0 | K26: 22800 | L26: Net Banking | M26: TXN770592655 | Q26: =IF(F30="Pending",CHOOSE(RANDBETWEEN(1,4),"UPI","Cash","Card","Net Banking"),0) -> UPI
A27: P00026 | B27: B0026 | C27: CUST1774 | D27: 46204 | E27: Checked-In | F27: Partial/Advanced | G27: =IF(Payment_Dataset[[#This Row],[Booking_Status]]="Completed",VLOOKUP(Payment_Dataset[[#This Row],[Booking_ID]],Booking_Dataset_Fact_Table[],11,FALSE)/VLOOKUP(Payment_Dataset[[#This Row],[Booking_Status]],Payment_Dataset!$N$6:$P$9,3,FALSE), IF(Payment_Dataset[[#This Row],[Booking_Status]]="Checked-In",VLOOKUP(Payment_Dataset[[#This Row],[Booking_ID]],Booking_Dataset_Fact_Table[],11,FALSE)*VLOOKUP(Payment_Dataset[[#This Row],[Booking_Status]],Payment_Dataset!$N$6:$P$9,3,FALSE), IF(Payment_Dataset[[#This Row],[Booking_Status]]="Cancelled",VLOOKUP(Payment_Dataset[[#This Row],[Booking_ID]],Booking_Dataset_Fact_Table[],11,FALSE)*VLOOKUP(Payment_Dataset[[#This Row],[Booking_Status]],Payment_Dataset!$N$6:$P$9,3,FALSE), IF(Payment_Dataset[[#This Row],[Booking_Status]]="Confirmed",0)))) -> 1750 | H27: =Payment_Dataset[[#This Row],[Total Amount]]-Payment_Dataset[[#This Row],[Amount_Paid]] -> 3250 | I27: 1750 | J27: 3250 | K27: 5000 | L27: Credit Card | M27: TXN777696747 | Q27: =IF(F31="Pending",CHOOSE(RANDBETWEEN(1,4),"UPI","Cash","Card","Net Banking"),0) -> 0
A28: P00027 | B28: B0027 | C28: CUST1505 | D28: 46096 | E28: Completed | F28: Paid | G28: =IF(Payment_Dataset[[#This Row],[Booking_Status]]="Completed",VLOOKUP(Payment_Dataset[[#This Row],[Booking_ID]],Booking_Dataset_Fact_Table[],11,FALSE)/VLOOKUP(Payment_Dataset[[#This Row],[Booking_Status]],Payment_Dataset!$N$6:$P$9,3,FALSE), IF(Payment_Dataset[[#This Row],[Booking_Status]]="Checked-In",VLOOKUP(Payment_Dataset[[#This Row],[Booking_ID]],Booking_Dataset_Fact_Table[],11,FALSE)*VLOOKUP(Payment_Dataset[[#This Row],[Booking_Status]],Payment_Dataset!$N$6:$P$9,3,FALSE), IF(Payment_Dataset[[#This Row],[Booking_Status]]="Cancelled",VLOOKUP(Payment_Dataset[[#This Row],[Booking_ID]],Booking_Dataset_Fact_Table[],11,FALSE)*VLOOKUP(Payment_Dataset[[#This Row],[Booking_Status]],Payment_Dataset!$N$6:$P$9,3,FALSE), IF(Payment_Dataset[[#This Row],[Booking_Status]]="Confirmed",0)))) -> 42000 | H28: =Payment_Dataset[[#This Row],[Total Amount]]-Payment_Dataset[[#This Row],[Amount_Paid]] -> 0 | I28: 42000 | J28: 0 | K28: 42000 | L28: Debit Card | M28: TXN769801732 | Q28: =IF(F32="Pending",CHOOSE(RANDBETWEEN(1,4),"UPI","Cash","Card","Net Banking"),0) -> Card
A29: P00028 | B29: B0028 | C29: CUST1280 | D29: 46176 | E29: Confirmed | F29: Pending | G29: =IF(Payment_Dataset[[#This Row],[Booking_Status]]="Completed",VLOOKUP(Payment_Dataset[[#This Row],[Booking_ID]],Booking_Dataset_Fact_Table[],11,FALSE)/VLOOKUP(Payment_Dataset[[#This Row],[Booking_Status]],Payment_Dataset!$N$6:$P$9,3,FALSE), IF(Payment_Dataset[[#This Row],[Booking_Status]]="Checked-In",VLOOKUP(Payment_Dataset[[#This Row],[Booking_ID]],Booking_Dataset_Fact_Table[],11,FALSE)*VLOOKUP(Payment_Dataset[[#This Row],[Booking_Status]],Payment_Dataset!$N$6:$P$9,3,FALSE), IF(Payment_Dataset[[#This Row],[Booking_Status]]="Cancelled",VLOOKUP(Payment_Dataset[[#This Row],[Booking_ID]],Booking_Dataset_Fact_Table[],11,FALSE)*VLOOKUP(Payment_Dataset[[#This Row],[Booking_Status]],Payment_Dataset!$N$6:$P$9,3,FALSE), IF(Payment_Dataset[[#This Row],[Booking_Status]]="Confirmed",0)))) -> 0 | H29: =Payment_Dataset[[#This Row],[Total Amount]]-Payment_Dataset[[#This Row],[Amount_Paid]] -> 10000 | I29: 0 | J29: 10000 | K29: 10000 | L29: UPI | M29: TXN829137701
A30: P00029 | B30: B0029 | C30: CUST1824 | D30: 46072 | E30: Confirmed | F30: Pending | G30: =IF(Payment_Dataset[[#This Row],[Booking_Status]]="Completed",VLOOKUP(Payment_Dataset[[#This Row],[Booking_ID]],Booking_Dataset_Fact_Table[],11,FALSE)/VLOOKUP(Payment_Dataset[[#This Row],[Booking_Status]],Payment_Dataset!$N$6:$P$9,3,FALSE), IF(Payment_Dataset[[#This Row],[Booking_Status]]="Checked-In",VLOOKUP(Payment_Dataset[[#This Row],[Booking_ID]],Booking_Dataset_Fact_Table[],11,FALSE)*VLOOKUP(Payment_Dataset[[#This Row],[Booking_Status]],Payment_Dataset!$N$6:$P$9,3,FALSE), IF(Payment_Dataset[[#This Row],[Booking_Status]]="Cancelled",VLOOKUP(Payment_Dataset[[#This Row],[Booking_ID]],Booking_Dataset_Fact_Table[],11,FALSE)*VLOOKUP(Payment_Dataset[[#This Row],[Booking_Status]],Payment_Dataset!$N$6:$P$9,3,FALSE), IF(Payment_Dataset[[#This Row],[Booking_Status]]="Confirmed",0)))) -> 0 | H30: =Payment_Dataset[[#This Row],[Total Amount]]-Payment_Dataset[[#This Row],[Amount_Paid]] -> 27500 | I30: 0 | J30: 27500 | K30: 27500 | L30: Net Banking | M30: TXN716627375
A31: P00030 | B31: B0030 | C31: CUST0815 | D31: 46204 | E31: Completed | F31: Paid | G31: =IF(Payment_Dataset[[#This Row],[Booking_Status]]="Completed",VLOOKUP(Payment_Dataset[[#This Row],[Booking_ID]],Booking_Dataset_Fact_Table[],11,FALSE)/VLOOKUP(Payment_Dataset[[#This Row],[Booking_Status]],Payment_Dataset!$N$6:$P$9,3,FALSE), IF(Payment_Dataset[[#This Row],[Booking_Status]]="Checked-In",VLOOKUP(Payment_Dataset[[#This Row],[Booking_ID]],Booking_Dataset_Fact_Table[],11,FALSE)*VLOOKUP(Payment_Dataset[[#This Row],[Booking_Status]],Payment_Dataset!$N$6:$P$9,3,FALSE), IF(Payment_Dataset[[#This Row],[Booking_Status]]="Cancelled",VLOOKUP(Payment_Dataset[[#This Row],[Booking_ID]],Booking_Dataset_Fact_Table[],11,FALSE)*VLOOKUP(Payment_Dataset[[#This Row],[Booking_Status]],Payment_Dataset!$N$6:$P$9,3,FALSE), IF(Payment_Dataset[[#This Row],[Booking_Status]]="Confirmed",0)))) -> 16500 | H31: =Payment_Dataset[[#This Row],[Total Amount]]-Payment_Dataset[[#This Row],[Amount_Paid]] -> 0 | I31: 16500 | J31: 0 | K31: 16500 | L31: Net Banking | M31: TXN626449772
A32: P00031 | B32: B0031 | C32: CUST1596 | D32: 46161 | E32: Confirmed | F32: Pending | G32: =IF(Payment_Dataset[[#This Row],[Booking_Status]]="Completed",VLOOKUP(Payment_Dataset[[#This Row],[Booking_ID]],Booking_Dataset_Fact_Table[],11,FALSE)/VLOOKUP(Payment_Dataset[[#This Row],[Booking_Status]],Payment_Dataset!$N$6:$P$9,3,FALSE), IF(Payment_Dataset[[#This Row],[Booking_Status]]="Checked-In",VLOOKUP(Payment_Dataset[[#This Row],[Booking_ID]],Booking_Dataset_Fact_Table[],11,FALSE)*VLOOKUP(Payment_Dataset[[#This Row],[Booking_Status]],Payment_Dataset!$N$6:$P$9,3,FALSE), IF(Payment_Dataset[[#This Row],[Booking_Status]]="Cancelled",VLOOKUP(Payment_Dataset[[#This Row],[Booking_ID]],Booking_Dataset_Fact_Table[],11,FALSE)*VLOOKUP(Payment_Dataset[[#This Row],[Booking_Status]],Payment_Dataset!$N$6:$P$9,3,FALSE), IF(Payment_Dataset[[#This Row],[Booking_Status]]="Confirmed",0)))) -> 0 | H32: =Payment_Dataset[[#This Row],[Total Amount]]-Payment_Dataset[[#This Row],[Amount_Paid]] -> 18800 | I32: 0 | J32: 18800 | K32: 18800 | L32: Debit Card | M32: TXN172366636
A33: P00032 | B33: B0032 | C33: CUST0879 | D33: 46117 | E33: Checked-In | F33: Partial/Advanced | G33: =IF(Payment_Dataset[[#This Row],[Booking_Status]]="Completed",VLOOKUP(Payment_Dataset[[#This Row],[Booking_ID]],Booking_Dataset_Fact_Table[],11,FALSE)/VLOOKUP(Payment_Dataset[[#This Row],[Booking_Status]],Payment_Dataset!$N$6:$P$9,3,FALSE), IF(Payment_Dataset[[#This Row],[Booking_Status]]="Checked-In",VLOOKUP(Payment_Dataset[[#This Row],[Booking_ID]],Booking_Dataset_Fact_Table[],11,FALSE)*VLOOKUP(Payment_Dataset[[#This Row],[Booking_Status]],Payment_Dataset!$N$6:$P$9,3,FALSE), IF(Payment_Dataset[[#This Row],[Booking_Status]]="Cancelled",VLOOKUP(Payment_Dataset[[#This Row],[Booking_ID]],Booking_Dataset_Fact_Table[],11,FALSE)*VLOOKUP(Payment_Dataset[[#This Row],[Booking_Status]],Payment_Dataset!$N$6:$P$9,3,FALSE), IF(Payment_Dataset[[#This Row],[Booking_Status]]="Confirmed",0)))) -> 8225 | H33: =Payment_Dataset[[#This Row],[Total Amount]]-Payment_Dataset[[#This Row],[Amount_Paid]] -> 15275 | I33: 8225 | J33: 15275 | K33: 23500 | L33: UPI | M33: TXN263094315
A34: P00033 | B34: B0033 | C34: CUST1721 | D34: 46149 | E34: Checked-In | F34: Partial/Advanced | G34: =IF(Payment_Dataset[[#This Row],[Booking_Status]]="Completed",VLOOKUP(Payment_Dataset[[#This Row],[Booking_ID]],Booking_Dataset_Fact_Table[],11,FALSE)/VLOOKUP(Payment_Dataset[[#This Row],[Booking_Status]],Payment_Dataset!$N$6:$P$9,3,FALSE), IF(Payment_Dataset[[#This Row],[Booking_Status]]="Checked-In",VLOOKUP(Payment_Dataset[[#This Row],[Booking_ID]],Booking_Dataset_Fact_Table[],11,FALSE)*VLOOKUP(Payment_Dataset[[#This Row],[Booking_Status]],Payment_Dataset!$N$6:$P$9,3,FALSE), IF(Payment_Dataset[[#This Row],[Booking_Status]]="Cancelled",VLOOKUP(Payment_Dataset[[#This Row],[Booking_ID]],Booking_Dataset_Fact_Table[],11,FALSE)*VLOOKUP(Payment_Dataset[[#This Row],[Booking_Status]],Payment_Dataset!$N$6:$P$9,3,FALSE), IF(Payment_Dataset[[#This Row],[Booking_Status]]="Confirmed",0)))) -> 2520 | H34: =Payment_Dataset[[#This Row],[Total Amount]]-Payment_Dataset[[#This Row],[Amount_Paid]] -> 4680 | I34: 2520 | J34: 4680 | K34: 7200 | L34: Cash | M34: TXN426987677
A35: P00034 | B35: B0034 | C35: CUST0330 | D35: 46025 | E35: Checked-In | F35: Partial/Advanced | G35: =IF(Payment_Dataset[[#This Row],[Booking_Status]]="Completed",VLOOKUP(Payment_Dataset[[#This Row],[Booking_ID]],Booking_Dataset_Fact_Table[],11,FALSE)/VLOOKUP(Payment_Dataset[[#This Row],[Booking_Status]],Payment_Dataset!$N$6:$P$9,3,FALSE), IF(Payment_Dataset[[#This Row],[Booking_Status]]="Checked-In",VLOOKUP(Payment_Dataset[[#This Row],[Booking_ID]],Booking_Dataset_Fact_Table[],11,FALSE)*VLOOKUP(Payment_Dataset[[#This Row],[Booking_Status]],Payment_Dataset!$N$6:$P$9,3,FALSE), IF(Payment_Dataset[[#This Row],[Booking_Status]]="Cancelled",VLOOKUP(Payment_Dataset[[#This Row],[Booking_ID]],Booking_Dataset_Fact_Table[],11,FALSE)*VLOOKUP(Payment_Dataset[[#This Row],[Booking_Status]],Payment_Dataset!$N$6:$P$9,3,FALSE), IF(Payment_Dataset[[#This Row],[Booking_Status]]="Confirmed",0)))) -> 13650 | H35: =Payment_Dataset[[#This Row],[Total Amount]]-Payment_Dataset[[#This Row],[Amount_Paid]] -> 25350 | I35: 13650 | J35: 25350 | K35: 39000 | L35: Cash | M35: TXN175696581
A36: P00035 | B36: B0035 | C36: CUST1686 | D36: 46164 | E36: Completed | F36: Paid | G36: =IF(Payment_Dataset[[#This Row],[Booking_Status]]="Completed",VLOOKUP(Payment_Dataset[[#This Row],[Booking_ID]],Booking_Dataset_Fact_Table[],11,FALSE)/VLOOKUP(Payment_Dataset[[#This Row],[Booking_Status]],Payment_Dataset!$N$6:$P$9,3,FALSE), IF(Payment_Dataset[[#This Row],[Booking_Status]]="Checked-In",VLOOKUP(Payment_Dataset[[#This Row],[Booking_ID]],Booking_Dataset_Fact_Table[],11,FALSE)*VLOOKUP(Payment_Dataset[[#This Row],[Booking_Status]],Payment_Dataset!$N$6:$P$9,3,FALSE), IF(Payment_Dataset[[#This Row],[Booking_Status]]="Cancelled",VLOOKUP(Payment_Dataset[[#This Row],[Booking_ID]],Booking_Dataset_Fact_Table[],11,FALSE)*VLOOKUP(Payment_Dataset[[#This Row],[Booking_Status]],Payment_Dataset!$N$6:$P$9,3,FALSE), IF(Payment_Dataset[[#This Row],[Booking_Status]]="Confirmed",0)))) -> 28800 | H36: =Payment_Dataset[[#This Row],[Total Amount]]-Payment_Dataset[[#This Row],[Amount_Paid]] -> 0 | I36: 28800 | J36: 0 | K36: 28800 | L36: Credit Card | M36: TXN637067756
A37: P00036 | B37: B0036 | C37: CUST1780 | D37: 46124 | E37: Confirmed | F37: Pending | G37: =IF(Payment_Dataset[[#This Row],[Booking_Status]]="Completed",VLOOKUP(Payment_Dataset[[#This Row],[Booking_ID]],Booking_Dataset_Fact_Table[],11,FALSE)/VLOOKUP(Payment_Dataset[[#This Row],[Booking_Status]],Payment_Dataset!$N$6:$P$9,3,FALSE), IF(Payment_Dataset[[#This Row],[Booking_Status]]="Checked-In",VLOOKUP(Payment_Dataset[[#This Row],[Booking_ID]],Booking_Dataset_Fact_Table[],11,FALSE)*VLOOKUP(Payment_Dataset[[#This Row],[Booking_Status]],Payment_Dataset!$N$6:$P$9,3,FALSE), IF(Payment_Dataset[[#This Row],[Booking_Status]]="Cancelled",VLOOKUP(Payment_Dataset[[#This Row],[Booking_ID]],Booking_Dataset_Fact_Table[],11,FALSE)*VLOOKUP(Payment_Dataset[[#This Row],[Booking_Status]],Payment_Dataset!$N$6:$P$9,3,FALSE), IF(Payment_Dataset[[#This Row],[Booking_Status]]="Confirmed",0)))) -> 0 | H37: =Payment_Dataset[[#This Row],[Total Amount]]-Payment_Dataset[[#This Row],[Amount_Paid]] -> 21000 | I37: 0 | J37: 21000 | K37: 21000 | L37: Net Banking | M37: TXN113685816
A38: P00037 | B38: B0037 | C38: CUST1171 | D38: 46165 | E38: Completed | F38: Paid | G38: =IF(Payment_Dataset[[#This Row],[Booking_Status]]="Completed",VLOOKUP(Payment_Dataset[[#This Row],[Booking_ID]],Booking_Dataset_Fact_Table[],11,FALSE)/VLOOKUP(Payment_Dataset[[#This Row],[Booking_Status]],Payment_Dataset!$N$6:$P$9,3,FALSE), IF(Payment_Dataset[[#This Row],[Booking_Status]]="Checked-In",VLOOKUP(Payment_Dataset[[#This Row],[Booking_ID]],Booking_Dataset_Fact_Table[],11,FALSE)*VLOOKUP(Payment_Dataset[[#This Row],[Booking_Status]],Payment_Dataset!$N$6:$P$9,3,FALSE), IF(Payment_Dataset[[#This Row],[Booking_Status]]="Cancelled",VLOOKUP(Payment_Dataset[[#This Row],[Booking_ID]],Booking_Dataset_Fact_Table[],11,FALSE)*VLOOKUP(Payment_Dataset[[#This Row],[Booking_Status]],Payment_Dataset!$N$6:$P$9,3,FALSE), IF(Payment_Dataset[[#This Row],[Booking_Status]]="Confirmed",0)))) -> 28000 | H38: =Payment_Dataset[[#This Row],[Total Amount]]-Payment_Dataset[[#This Row],[Amount_Paid]] -> 0 | I38: 28000 | J38: 0 | K38: 28000 | L38: Net Banking | M38: TXN662109116
A39: P00038 | B39: B0038 | C39: CUST0613 | D39: 46139 | E39: Confirmed | F39: Pending | G39: =IF(Payment_Dataset[[#This Row],[Booking_Status]]="Completed",VLOOKUP(Payment_Dataset[[#This Row],[Booking_ID]],Booking_Dataset_Fact_Table[],11,FALSE)/VLOOKUP(Payment_Dataset[[#This Row],[Booking_Status]],Payment_Dataset!$N$6:$P$9,3,FALSE), IF(Payment_Dataset[[#This Row],[Booking_Status]]="Checked-In",VLOOKUP(Payment_Dataset[[#This Row],[Booking_ID]],Booking_Dataset_Fact_Table[],11,FALSE)*VLOOKUP(Payment_Dataset[[#This Row],[Booking_Status]],Payment_Dataset!$N$6:$P$9,3,FALSE), IF(Payment_Dataset[[#This Row],[Booking_Status]]="Cancelled",VLOOKUP(Payment_Dataset[[#This Row],[Booking_ID]],Booking_Dataset_Fact_Table[],11,FALSE)*VLOOKUP(Payment_Dataset[[#This Row],[Booking_Status]],Payment_Dataset!$N$6:$P$9,3,FALSE), IF(Payment_Dataset[[#This Row],[Booking_Status]]="Confirmed",0)))) -> 0 | H39: =Payment_Dataset[[#This Row],[Total Amount]]-Payment_Dataset[[#This Row],[Amount_Paid]] -> 26800 | I39: 0 | J39: 26800 | K39: 26800 | L39: Debit Card | M39: TXN457601586
A40: P00039 | B40: B0039 | C40: CUST0096 | D40: 46065 | E40: Completed | F40: Paid | G40: =IF(Payment_Dataset[[#This Row],[Booking_Status]]="Completed",VLOOKUP(Payment_Dataset[[#This Row],[Booking_ID]],Booking_Dataset_Fact_Table[],11,FALSE)/VLOOKUP(Payment_Dataset[[#This Row],[Booking_Status]],Payment_Dataset!$N$6:$P$9,3,FALSE), IF(Payment_Dataset[[#This Row],[Booking_Status]]="Checked-In",VLOOKUP(Payment_Dataset[[#This Row],[Booking_ID]],Booking_Dataset_Fact_Table[],11,FALSE)*VLOOKUP(Payment_Dataset[[#This Row],[Booking_Status]],Payment_Dataset!$N$6:$P$9,3,FALSE), IF(Payment_Dataset[[#This Row],[Booking_Status]]="Cancelled",VLOOKUP(Payment_Dataset[[#This Row],[Booking_ID]],Booking_Dataset_Fact_Table[],11,FALSE)*VLOOKUP(Payment_Dataset[[#This Row],[Booking_Status]],Payment_Dataset!$N$6:$P$9,3,FALSE), IF(Payment_Dataset[[#This Row],[Booking_Status]]="Confirmed",0)))) -> 6000 | H40: =Payment_Dataset[[#This Row],[Total Amount]]-Payment_Dataset[[#This Row],[Amount_Paid]] -> 0 | I40: 6000 | J40: 0 | K40: 6000 | L40: Net Banking | M40: TXN926846023
... A607: P00606 | B607: B0750 | C607: CUST0895 | D607: 46105 | E607: Confirmed | F607: Pending | G607: =IF(Payment_Dataset[[#This Row],[Booking_Status]]="Completed",VLOOKUP(Payment_Dataset[[#This Row],[Booking_ID]],Booking_Dataset_Fact_Table[],11,FALSE)/VLOOKUP(Payment_Dataset[[#This Row],[Booking_Status]],Payment_Dataset!$N$6:$P$9,3,FALSE), IF(Payment_Dataset[[#This Row],[Booking_Status]]="Checked-In",VLOOKUP(Payment_Dataset[[#This Row],[Booking_ID]],Booking_Dataset_Fact_Table[],11,FALSE)*VLOOKUP(Payment_Dataset[[#This Row],[Booking_Status]],Payment_Dataset!$N$6:$P$9,3,FALSE), IF(Payment_Dataset[[#This Row],[Booking_Status]]="Cancelled",VLOOKUP(Payment_Dataset[[#This Row],[Booking_ID]],Booking_Dataset_Fact_Table[],11,FALSE)*VLOOKUP(Payment_Dataset[[#This Row],[Booking_Status]],Payment_Dataset!$N$6:$P$9,3,FALSE), IF(Payment_Dataset[[#This Row],[Booking_Status]]="Confirmed",0)))) -> 0 | H607: =Payment_Dataset[[#This Row],[Total Amount]]-Payment_Dataset[[#This Row],[Amount_Paid]] -> 19200 | I607: 0 | J607: 19200 | K607: 19200 | L607: Credit Card | M607: TXN965736485

Sheet Employee_Dataset
A1: Employee_ID | B1: Employee_Name | C1: Gender | D1: Age | E1: Department | F1: Designation | G1: Salary | H1: State | I1: City | J1: Joining_Date | K1: Shift | L1: Phone_Number
A2: EMP001 | B2: Jairaj Kala | C2: Male | D2: 37 | E2: Finance | F2: Finance Executive | G2: 30915 | H2: Maharastra | I2: Mumbai | J2: 44698 | K2: Night | L2: 7094725306
A3: EMP002 | B3: Vidhi Puri | C3: Female | D3: 42 | E3: HR | F3: HR Executive | G3: 21506 | H3: Maharastra | I3: Mumbai | J3: 45735 | K3: Morning | L3: 8635901217
A4: EMP003 | B4: Victor Ranganathan | C4: Male | D4: 37 | E4: Finance | F4: Finance Executive | G4: 58804 | H4: Maharastra | I4: Mumbai | J4: 45403 | K4: Evening | L4: 7002851911
A5: EMP004 | B5: Sai Deshpande | C5: Male | D5: 20 | E5: Maintenance | F5: Technician | G5: 65180 | H5: Gujrat | I5: Surat | J5: 44859 | K5: Evening | L5: 8519709347
A6: EMP005 | B6: Atharv Bumb | C6: Male | D6: 22 | E6: Maintenance | F6: Electrician | G6: 21276 | H6: Madhya Pradesh | I6: Indore | J6: 43978 | K6: Morning | L6: 6028191529
A7: EMP006 | B7: Amaira Kunda | C7: Female | D7: 26 | E7: Security | F7: Security Supervisor | G7: 29265 | H7: Karnataka | I7: Bangluru | J7: 45704 | K7: Morning | L7: 7252243520
A8: EMP007 | B8: Shivansh Vig | C8: Male | D8: 35 | E8: Kitchen | F8: Sous Chef | G8: 55010 | H8: Karnataka | I8: Mysuru | J8: 44354 | K8: Evening | L8: 7992907643
A9: EMP008 | B9: Januja Yogi | C9: Female | D9: 34 | E9: HR | F9: HR Manager | G9: 24219 | H9: Madhya Pradesh | I9: Bhopa | J9: 44382 | K9: Evening | L9: 8257786253
A10: EMP009 | B10: Lucky Trivedi | C10: Male | D10: 48 | E10: Security | F10: Security Supervisor | G10: 45388 | H10: Maharastra | I10: Nashik | J10: 45992 | K10: Morning | L10: 9121243116
A11: EMP010 | B11: Aradhana Batra | C11: Female | D11: 42 | E11: Housekeeping | F11: Supervisor | G11: 67331 | H11: Maharastra | I11: Pune | J11: 45310 | K11: Evening | L11: 7169508090
A12: EMP011 | B12: Balvan Kanda | C12: Male | D12: 27 | E12: Spa | F12: Spa Therapist | G12: 28254 | H12: Maharastra | I12: Mumbai | J12: 43824 | K12: Evening | L12: 9258533142
A13: EMP058 | B13: Harshil Chaudhari | C13: Male | D13: 34 | E13: Kitchen | F13: Sous Chef | G13: 53606 | H13: Madhya Pradesh | I13: Indore | J13: 44962 | K13: Evening | L13: 7211189198
... A145: EMP144 | B145: Vyanjana Gola | C145: Female | D145: 33 | E145: Front Office | F145: Front Desk Executive | G145: 52315 | H145: Karnataka | I145: Bangluru | J145: 45345 | K145: Evening | L145: 6260055022

Sheet Customer_Dataset
A1: Customer_ID | B1: Customer_Name | C1: Age | D1: Gender | E1: City | F1: State | G1: Phone_Number
A2: CUST0001 | B2: Maanas Dugal | C2: 54 | D2: Male | E2: Ajmer | F2: Rajasthan | G2: 8268439701
A3: CUST0002 | B3: Banjeet Bajwa | C3: 35 | D3: Male | E3: Margao | F3: Goa | G3: 8983139894
A4: CUST0003 | B4: Rachana Chauhan | C4: 55 | D4: Female | E4: Amritsar | F4: Punjab | G4: 6242988084
A5: CUST0004 | B5: Dipta Puri | C5: 34 | D5: Female | E5: Bhagalpur | F5: Bihar | G5: 7385201824
A6: CUST0005 | B6: Oni Madan | C6: 51 | D6: Female | E6: Udaipur | F6: Rajasthan | G6: 8396434475
A7: CUST0006 | B7: Neha Kibe | C7: 20 | D7: Female | E7: Dwarka | F7: Delhi | G7: 7108906806
A8: CUST0007 | B8: Nitara Arya | C8: 35 | D8: Female | E8: Kolkata | F8: West Bengal | G8: 8885082109
A9: CUST0008 | B9: Orinder Aurora | C9: 44 | D9: Male | E9: Thrissur | F9: Kerala | G9: 8798358610
A10: CUST0009 | B10: Ucchal Grover | C10: 37 | D10: Female | E10: Thiruvananthapuram | F10: Kerala | G10: 7796466608
A11: CUST0010 | B11: Chatresh Randhawa | C11: 24 | D11: Male | E11: Nizamabad | F11: Telangana | G11: 7495646103
A12: CUST0011 | B12: Balendra Cheema | C12: 47 | D12: Male | E12: Siliguri | F12: West Bengal | G12: 6179410081
A13: CUST0012 | B13: Peter Pau | C13: 54 | D13: Male | E13: Gwalior | F13: Madhya Pradesh | G13: 8424873173
... A1831: CUST1830 | B1831: Dayita Memon | C1831: 38 | D1831: Female | E1831: Karol Bagh | F1831: Delhi | G1831: 8870298222
